{"id":66192645,"topNeighbourId":66192646,"bottomNeighbourId":66192644,"leftNeighbourId":66193157,"rightNeighbourId":66192133,"shadowBonusOnEntities":-1,"cells":[{"l":66},{"l":66},{"l":66},{"l":66},{"l":66},{"l":66},{"l":66},{"l":66},{"l":66},{"l":66},{"l":66},{"l":66},{"l":66},{"l":66},{"l":66},{"l":66},{"l":66},{"l":66},{"l":66},{"l":66},{"l":66},{"l":66},{"l":66},{"l":66},{"l":66},{"l":66},{"l":66},{"l":66},{"l":2},{"l":66},{"l":2},{"l":66},{"l":66},{"l":66},{"l":66},{"l":66},{"l":66},{"l":66},{"l":66},{"l":66},{"l":66},{"l":66},{"l":66},{"l":66},{"l":66},{"l":66},{"l":66},{"l":66},{"l":66},{"l":66},{"l":66},{"l":66},{"l":66},{"l":66},{"l":66},{"l":66},{"l":2},{"l":66},{"l":2},{"l":66},{"l":66},{"l":66},{"l":66},{"l":66},{"l":66},{"l":66},{"l":66},{"l":66},{"l":66},{"l":66},{"l":2},{"l":66},{"l":2},{"l":66},{"l":66},{"l":66},{"l":66},{"l":66},{"l":66},{"l":66},{"l":66},{"l":66},{"l":66},{"l":66},{"l":2},{"l":66},{"l":2},{"l":66},{"l":66},{"l":66},{"l":66},{"l":66},{"l":66},{"l":66},{"l":66},{"l":66},{"l":66},{"l":66},{"l":2},{"l":66},{"l":2},{"l":66},{"l":66},{"l":66},{"l":66},{"l":66},{"l":66},{"l":66},{"l":66},{"l":66},{"l":66},{"l":66},{"l":2},{"l":66},{"l":66},{"l":66},{"l":66},{"l":66},{"l":66},{"l":66},{"l":66},{"l":66},{"l":66},{"l":66},{"l":66},{"l":66},{"l":2},{"l":66},{"l":66},{"l":66},{"l":66},{"l":66},{"l":66},{"l":66},{"l":66},{"l":66},{"l":66},{"l":66},{"l":66},{"l":66},{"l":2},{"l":66},{"l":66},{"l":66},{"l":66},{"l":66},{"l":66},{"l":66},{"l":66},{"l":66},{"l":66},{"l":66},{"l":66},{"l":66},{"l":2},{"l":66},{"l":66},{"l":66},{"l":66},{"l":66},{"l":66},{"l":66},{"l":66},{"l":66},{"l":66},{"l":66},{"l":66},{"l":66},{"l":2},{"l":66},{"l":66},{"l":66},{"l":66},{"l":66},{"l":66},{"l":66},{"l":66},{"l":66},{"l":66},{"l":66},{"l":66},{"l":66},{"l":66},{"l":66},{"l":66},{"l":66},{"l":66},{"l":66},{"l":66},{"l":66},{"l":66},{"l":66},{"l":66},{"l":66},{"l":66},{"l":66},{"l":66},{"l":66},{"l":66},{"l":66},{"l":66},{"l":66},{"l":66},{"l":66},{"l":66},{"l":66},{"l":66},{"l":66},{"l":66},{"l":66},{"l":66},{"l":66},{"l":66},{"l":66},{"l":66},{"l":66},{"l":66},{"l":66},{"l":66},{"l":66},{"l":2},{"l":66},{"l":66},{"l":66},{"l":66},{"l":66},{"l":66},{"l":66},{"l":66},{"l":66},{"l":66},{"l":66},{"l":66},{"l":66},{"l":66},{"l":66},{"l":66},{"l":66},{"l":66},{"l":66},{"l":66},{"l":66},{"l":66},{"l":66},{"l":66},{"l":66},{"l":66},{"l":66},{"l":2},{"l":66},{"l":66},{"l":67,"c":-125},{"l":66},{"l":66},{"l":66},{"l":66},{"l":66},{"l":66},{"l":66},{"l":66},{"l":66},{"l":66},{"l":66},{"l":66},{"l":67},{"l":67,"c":1},{"l":66},{"l":66},{"l":66},{"l":66},{"l":66},{"l":66},{"l":66},{"l":66},{"l":66},{"l":66},{"l":2},{"l":67},{"l":67},{"l":67,"c":-125},{"l":66},{"l":66},{"l":66},{"l":66},{"l":66},{"l":66},{"l":66},{"l":66},{"l":66},{"l":66},{"l":2},{"l":2},{"l":67},{"l":67,"c":1},{"l":66},{"l":66},{"l":66},{"l":66},{"l":66},{"l":66},{"l":66},{"l":66},{"l":66},{"l":66},{"l":2},{"l":67},{"l":67},{"l":67,"c":-125},{"l":66},{"l":66},{"l":66},{"l":66},{"l":66},{"l":66},{"l":66},{"l":66},{"l":66},{"l":66},{"l":3},{"l":3},{"l":67},{"l":67,"c":1},{"l":66},{"l":66},{"l":66},{"l":66},{"l":66},{"l":66},{"l":66},{"l":66},{"l":66},{"l":67},{"l":3},{"l":67},{"l":67},{"l":67,"c":-125},{"l":66},{"l":66},{"l":66},{"l":66},{"l":66},{"l":66},{"l":66},{"l":66},{"l":66},{"l":67},{"l":3},{"l":3},{"l":67},{"l":67,"c":1},{"l":66},{"l":66},{"l":66},{"l":66},{"l":66},{"l":66},{"l":66},{"l":67},{"l":67},{"l":3},{},{"l":3},{"l":67},{"l":67,"c":-125},{"l":66},{"l":66},{"l":66},{"l":66},{"l":66},{"l":66},{"l":66},{"l":67},{"l":67},{"l":3},{},{},{"l":2},{"l":67,"c":1},{"l":66},{"l":66},{"l":66},{"l":66},{"l":66},{"l":66},{"l":66},{"l":67},{"l":67},{"l":67},{},{},{"l":67},{"l":67,"c":-125},{"l":66},{"l":66},{"l":66},{"l":66},{"l":66},{"l":66},{"l":66},{"l":67},{"l":2},{"l":67},{"l":67},{"l":67},{"l":67},{"l":67,"c":1},{"l":66},{"l":66},{"l":66},{"l":66},{"l":66},{"l":66},{"l":66},{"l":67},{"l":67},{"l":67},{"l":67},{"l":67},{"l":67},{"l":67,"c":-125},{"l":66},{"l":66},{"l":66},{"l":66},{"l":66},{"l":66},{"l":66},{"l":67},{"l":195},{"l":67},{"l":67},{"l":67},{"l":67},{"l":67,"c":1},{"l":66},{"l":66},{"l":66},{"l":66},{"l":66},{"l":66},{"l":67},{"l":67},{"l":67},{"l":67},{"l":67},{"l":67},{"l":67},{"l":67,"c":-125},{"l":66},{"l":66},{"l":66},{"l":66},{"l":66},{"l":66},{"l":66},{"l":67},{"l":67},{"l":67},{"l":67},{"l":67},{"l":67},{"l":3,"c":1},{"l":66},{"l":66},{"l":66},{"l":66},{"l":66},{"l":66},{"l":67},{"l":67},{"l":67},{"l":67},{"l":67},{"l":67},{"l":67},{"l":67,"c":-125},{"l":66},{"l":66},{"l":66},{"l":66},{"l":66},{"l":66},{"l":67},{"l":67},{"l":67},{"l":67},{"l":67},{"l":67},{"l":67},{"l":3,"c":1},{"l":66},{"l":66},{"l":66},{"l":66},{"l":66},{"l":66},{"l":67},{"l":67},{"l":67},{"l":67},{"l":67},{"l":67},{"l":3},{"l":67,"c":-125},{"l":66},{"l":66},{"l":66},{"l":66},{"l":66},{"l":66},{"l":66},{"l":67},{"l":67},{"l":67},{"l":67},{"l":67},{"l":67},{"l":3,"c":1},{"l":66},{"l":66},{"l":66},{"l":66},{"l":66},{"l":66},{"l":67},{"l":67},{"l":67},{"l":67},{"l":67},{"l":67},{"l":3},{"l":67,"c":-125},{"l":66},{"l":66},{"l":66},{"l":66},{"l":66},{"l":66},{"l":66},{"l":67,"c":4},{"l":67,"c":4},{"l":67,"c":4},{"l":67,"c":4},{"l":67,"c":4},{"l":67,"c":4},{"l":3,"c":5},{"l":66},{"l":66},{"l":66},{"l":66},{"l":66},{"l":66},{"l":67,"c":2},{"l":67,"c":14},{"l":67,"c":14},{"l":67,"c":14},{"l":67,"c":14},{"l":67,"c":14},{"l":3,"c":14},{"l":3,"c":-115}],"midgroundLayer":{"154":[{"g":29086,"x":-88,"y":24.5,"hue":[0,0,0],"cx":-35,"cw":146,"ch":250},{"look":1797,"x":12,"y":72.5,"hue":[0,0,0],"dmin":5,"dmax":10,"anim":1,"astc":1,"sx":-1}],"169":[{"g":22179,"x":62,"y":227,"hue":[0,0,0],"cw":48,"ch":33}],"172":[{"look":1610,"x":334,"y":238,"hue":[0,0,0],"dmin":1,"dmax":15,"anim":1,"astc":1}],"183":[{"g":22180,"x":104,"y":255.5,"hue":[0,0,0],"cw":27,"ch":24}],"265":[{"g":20751,"x":1056,"y":-49,"hue":[0,0,0],"cw":100,"ch":96}],"296":[{"g":28240,"x":702,"y":119.5,"hue":[0,0,0],"sx":-1,"cw":893,"ch":319}],"373":[{"g":22178,"x":728,"y":516,"hue":[0,0,0],"cw":90,"ch":66}],"374":[{"g":29088,"x":818,"y":280,"hue":[0,0,0],"cw":169,"ch":322},{"g":29207,"x":817,"y":310,"hue":[0,0,0],"cw":145,"ch":285},{"look":1734,"x":860,"y":529,"hue":[0,0,0],"dmin":3,"dmax":12,"anim":1,"astc":1}],"376":[{"g":22181,"x":1027,"y":535,"hue":[0,0,0],"cw":39,"ch":28},{"look":1842,"x":1032,"y":559,"hue":[0,0,0],"id":465969}],"387":[{"g":22179,"x":793,"y":549.5,"hue":[0,0,0],"cw":48,"ch":33}],"389":[{"g":701097,"x":949,"y":490.5,"hue":[0,0,0],"cw":76,"ch":105}],"390":[{"g":701121,"x":1045,"y":544.5,"hue":[0,0,0],"cw":48,"ch":39}],"391":[],"400":[{"look":1842,"x":688,"y":602,"hue":[0,0,0],"id":465970}],"401":[{"g":22180,"x":749,"y":578,"hue":[0,0,0],"cw":27,"ch":24}],"404":[{"g":22179,"x":1008,"y":571,"hue":[0,0,0],"cw":48,"ch":33}],"413":[{"g":22181,"x":640,"y":599.5,"hue":[0,0,0],"cw":39,"ch":28},{"g":701119,"x":603,"y":592.5,"hue":[0,0,0],"cw":48,"ch":39}],"436":[{"look":1636,"x":215,"y":666.5,"hue":[-48,-46,-31],"dmin":8,"dmax":15,"anim":1,"astc":1,"sx":-1}],"462":[{"g":20750,"x":-59,"y":273.5,"hue":[0,0,0],"cx":-6,"cw":141,"ch":159}],"512":[{"g":22181,"x":683,"y":750,"hue":[0,0,0],"cw":39,"ch":28}],"526":[{"g":22179,"x":707,"y":764.5,"hue":[0,0,0],"cw":48,"ch":33}],"540":[{"g":28240,"x":1175,"y":485,"hue":[0,0,0],"sx":-1,"cw":893,"ch":319}],"543":[{"g":20751,"x":884,"y":381,"hue":[0,0,0],"cw":100,"ch":96}],"560":[{"g":29092,"x":998,"y":662.5,"hue":[0,0,0],"cw":215,"ch":188},{"g":29208,"x":1040,"y":745.5,"hue":[0,0,0],"cw":147,"ch":105}]},"atlasLayout":{"width":412,"height":571,"graphicsPositions":{"20750":{"sx":218,"sy":253,"sw":141,"sh":159,"cx":6},"20751":{"sx":218,"sy":414,"sw":100,"sh":96},"22178":{"sx":320,"sy":182,"sw":90,"sh":66},"22179":{"sx":361,"sy":291,"sw":48,"sh":33},"22180":{"sx":172,"sy":283,"sw":27,"sh":24},"22181":{"sx":172,"sy":253,"sw":39,"sh":28},"28240":{"sx":1,"sy":515,"sw":134,"sh":48,"cw":893,"ch":319},"29086":{"sx":172,"sy":1,"sw":146,"sh":250,"cx":35},"29088":{"sx":1,"sy":1,"sw":169,"sh":322},"29092":{"sx":1,"sy":325,"sw":215,"sh":188},"29207":{"sx":320,"sy":1,"sw":91,"sh":179,"cw":145,"ch":285},"29208":{"sx":218,"sy":512,"sw":81,"sh":58,"cw":147,"ch":105},"701097":{"sx":320,"sy":414,"sw":76,"sh":105},"701119":{"sx":137,"sy":515,"sw":48,"sh":39},"701121":{"sx":361,"sy":250,"sw":48,"sh":39}}}}