{"id":111412737,"topNeighbourId":111412736,"bottomNeighbourId":111412738,"leftNeighbourId":111412225,"rightNeighbourId":111413249,"shadowBonusOnEntities":-1,"cells":[{"l":2},{"l":2},{"l":2},{"l":2},{"l":2},{"l":2},{"l":2},{"l":2},{"l":2},{"l":2},{"l":2},{"l":2},{"l":2},{"l":2},{"l":2},{"l":2},{"l":2},{"l":2},{"l":2},{"l":2},{"l":2},{"l":2},{"l":2},{"l":2},{"l":2},{"l":2},{"l":2},{"l":2},{"l":2},{"l":2},{"l":2},{"l":2},{"l":2},{"l":2},{"l":2},{"l":2},{"l":2},{"l":2},{"l":2},{"l":2},{"l":2},{"l":2},{"l":2},{"l":2},{"l":2},{"l":2},{"l":2},{"l":2},{"l":2},{"l":2},{"l":2},{"l":2},{"l":2},{"l":2},{"l":2},{"l":2},{"l":2},{"l":2},{"l":2},{"l":2},{"l":2},{"l":2},{"l":2},{"l":2},{"l":2},{"l":2},{"l":2},{"l":2},{"l":2},{"l":2},{"l":2},{"l":2},{"l":2},{"l":2},{"l":2},{"l":2},{"l":2},{"l":2},{"l":2},{"l":2},{"l":2},{"l":2},{"l":2},{"l":2},{"l":2},{"l":2},{"l":2},{"l":2},{"l":2},{"l":2},{"l":2},{"l":2},{"l":2},{"l":2},{"l":2},{"l":2},{"l":2},{"l":2},{"l":2},{"l":2},{"l":2},{"l":2},{"l":2},{"l":2},{"l":2},{"l":2},{"l":2},{"l":2},{"l":2},{"l":2},{"l":2},{"l":2},{"l":2},{"l":2},{"l":2},{"l":2},{"l":2},{"l":2},{"l":2},{"l":2},{"l":2},{"l":2},{"l":2},{"l":2},{"l":2},{"l":2},{"l":2},{"l":2},{"l":2},{"l":2},{"l":2},{"l":2},{"l":2},{"l":2},{"l":2},{"l":2},{"l":2},{"l":2},{"l":2},{"l":2},{"l":2},{"l":2},{"l":2},{"l":2},{"l":2},{"l":2},{"l":2},{"l":2},{"l":2},{"l":2},{"l":2},{"l":2},{"l":2},{"l":2},{"l":2},{"l":2},{"l":2},{"l":2},{"l":2},{"l":2},{"l":2},{"l":2},{"l":2},{"l":2},{"l":2},{"l":2},{"l":2},{"l":2},{"l":2},{"l":2},{"l":2},{"l":2},{"l":66},{"l":2},{"l":2},{"l":2},{"l":2},{"l":2},{"l":2},{"l":2},{"l":2},{"l":2},{"l":2},{"l":2},{"l":2},{"l":2},{"l":2},{"l":2},{"l":2},{"l":2},{"l":2},{"l":2},{"l":2},{"l":2},{"l":2},{"l":2},{"l":2},{"l":2},{"l":2},{"l":2},{"l":66},{"l":2},{"l":2},{"l":2},{"l":2},{"l":2},{"l":2},{"l":2},{"l":2},{"l":2},{"l":2},{"l":2},{"l":2},{"l":66},{"l":2},{"l":2},{"l":2},{"l":2},{"l":2},{"l":2},{"l":2},{"l":2},{"l":2},{"l":2},{"l":2},{"l":2},{"l":66},{"l":66},{"l":2},{"l":2},{"l":2},{},{"l":2},{"l":2},{"l":2},{"l":2},{"l":2},{"l":2},{"l":2},{"l":2},{"l":2},{"l":2},{"l":2},{"l":2},{"l":2},{},{"l":2},{},{"l":2},{"l":2},{"l":2},{"l":2},{"l":2},{"l":2},{"l":2},{"l":2},{"l":2},{"l":2},{"l":66},{"l":66},{},{},{},{"l":2},{"l":2},{"l":2},{"l":2},{"l":2},{"l":2},{"l":2},{"l":2},{"l":66},{"l":67},{"l":67},{},{"l":66},{},{"l":2},{"l":2},{"l":2},{"l":2},{"l":2},{"l":2},{"l":2},{"l":2},{},{"l":67},{"l":67},{"l":67},{"l":67},{"l":67},{},{"l":2},{"l":2},{},{"l":66},{"l":2},{"l":2},{"l":64},{"l":67},{"l":67},{"l":67},{"l":67},{"l":67},{"l":67},{},{"l":2},{"l":2},{},{"l":66},{"l":2},{"l":2},{"l":66},{"l":67},{"l":67},{"l":67},{"l":67},{"l":67},{"l":67},{},{"l":2},{"l":2},{"l":3},{"l":66},{"l":2},{"l":66},{"l":67},{"l":67},{"l":67},{"l":67},{"l":66},{"l":67},{"l":67},{},{"l":2},{"l":2},{},{"l":67},{},{},{"l":67},{"l":67},{"l":67},{"l":67},{"l":66},{"l":66},{"l":67},{},{},{"l":2},{"l":3},{"l":67},{},{"l":67},{"l":67},{"l":67},{"l":67},{"l":66},{"l":66},{"l":67},{"l":2},{"l":3},{},{"l":2},{"l":2},{"l":3},{"l":66},{"l":66},{"l":67},{"l":3},{"l":67},{"l":66},{"l":66},{"l":67},{"l":3},{"l":3},{"l":3},{},{"l":2},{"l":67},{"l":67},{"l":67},{"l":3},{"l":3},{"l":67},{"l":66},{"l":67},{"l":3},{"l":3},{"l":3},{},{"l":2},{"l":2},{"l":2},{"l":67},{"l":67},{"l":67},{"l":2},{"l":3},{"l":67},{"l":3},{"l":3},{"l":3},{"l":3},{},{"l":2},{"l":2},{"l":2},{"l":67},{"l":67},{"f":10,"l":7,"s":-5},{"l":2},{"l":3},{"l":67},{"l":3},{"l":3},{"l":3},{"l":66},{"l":66},{"l":2},{"l":2},{"l":2},{"l":2},{"l":67},{"l":67},{"f":10,"l":7,"s":-5},{"l":3},{"l":3},{"l":3},{"l":3},{"l":3},{"l":66},{"l":66},{"l":2},{"l":2},{"l":2},{"l":66},{"l":67},{"l":67},{"l":67},{"l":2},{"l":3},{"l":3},{"l":3},{},{"l":66},{"l":66},{"l":2},{"l":2},{"l":2},{"l":2},{"l":66},{"l":67},{"l":67},{"l":66},{"l":2},{"l":3},{"l":3},{},{"l":66},{"l":66},{"l":2},{"l":2},{"l":2},{"l":2},{"l":66},{"l":67},{"l":67},{"f":10,"l":7,"s":-5},{"l":67},{"l":3},{"l":2},{"l":2},{"l":66},{"l":2},{"l":2},{"l":2},{"l":2},{"l":2},{"l":2},{"l":2},{"l":3},{"l":67},{"l":67},{"l":3},{"l":2},{"l":2},{"l":66},{"l":2},{"l":2},{"l":2},{"l":2},{"l":2},{"l":2},{"l":66},{"l":67},{"l":67},{"l":3},{},{"l":2},{"l":2},{"l":2},{"l":2},{"l":2},{"l":2},{"l":2},{"l":2},{"l":2},{"l":2},{"l":2},{"l":67},{"l":67},{},{"l":66},{"l":2},{"l":66},{"l":2},{"l":2},{"l":2},{"l":2},{"l":2},{"l":2},{"l":2},{"l":2},{"l":67},{"l":2},{},{"l":66},{"l":2},{"l":2},{"l":2},{"l":2},{"l":2},{"l":2},{"l":2},{"l":2},{"l":2},{"l":2},{"l":2},{"l":3},{"l":66},{"l":66},{"l":2},{"l":2},{"l":2},{"l":2},{"l":2},{"l":2},{"l":2},{"l":2},{"l":2},{"l":2},{"l":2},{"l":67},{"l":66},{"l":66},{"l":2},{"l":2},{"l":2},{"l":2}],"midgroundLayer":{"260":[{"g":7945,"x":715,"y":337,"hue":[-6,-26,-48],"sx":-1,"cw":71,"ch":64},{"g":29283,"x":657,"y":304,"hue":[-13,-27,-59],"cw":49,"ch":51},{"look":1882,"x":678,"y":329,"hue":[0,0,0],"anim":1}],"261":[{"g":41517,"x":723,"y":212,"hue":[-9,-19,-32],"cw":61,"ch":203},{"g":41517,"x":723,"y":42,"hue":[-9,-19,-32],"cw":61,"ch":203},{"g":40498,"x":712,"y":356,"hue":[-9,-19,-32],"cw":71,"ch":66}],"262":[{"g":41540,"x":817,"y":29,"hue":[-26,-36,-48],"cw":131,"ch":315},{"g":41605,"x":949,"y":215,"hue":[2,-14,-45],"sx":-1,"cw":184,"ch":281}],"266":[{"g":41539,"x":-43,"y":159.5,"hue":[-76,-83,-93],"sx":-1,"cw":10,"ch":313},{"g":41539,"x":-43,"y":29.5,"hue":[-76,-83,-93],"sx":-1,"cw":10,"ch":313},{"g":41511,"x":-84,"y":388.5,"hue":[-53,-62,-74],"cw":92,"ch":70},{"g":41521,"x":140,"y":-57.5,"hue":[-68,-77,-89],"sx":-1,"cw":144,"ch":136}],"269":[{"g":4269,"x":289,"y":-55.5,"hue":[-128,-128,-128],"cw":26,"ch":171}],"271":[{"g":34491,"x":510,"y":245.5,"hue":[-39,-52,-68],"sx":-1,"cw":61,"ch":50},{"g":34490,"x":478,"y":299.5,"hue":[-66,-82,-99],"sx":-1,"cw":58,"ch":131}],"272":[{"look":1787,"x":559,"y":68.5,"hue":[0,0,0],"dmin":20,"dmax":25,"anim":1}],"274":[{"g":41595,"x":707,"y":322.5,"hue":[-5,-20,-52],"cw":56,"ch":99},{"g":41521,"x":635,"y":-56.5,"hue":[-28,-37,-47],"cw":144,"ch":136}],"276":[{"g":40920,"x":927,"y":290.5,"hue":[-18,-31,-58],"sx":-1,"id":480550,"cw":112,"ch":154}],"280":[{"g":34534,"x":35,"y":223,"hue":[-80,-90,-105],"sx":-1,"cw":73,"ch":232},{"g":41576,"x":-23,"y":300,"hue":[-65,-75,-88],"cw":19,"ch":104},{"g":41576,"x":-23,"y":262,"hue":[-65,-75,-88],"cw":19,"ch":104}],"285":[{"g":31316,"x":486,"y":252,"hue":[-41,-51,-62],"sx":-1,"cw":86,"ch":197},{"g":11221,"x":427,"y":269,"hue":[-56,-78,-102],"cw":52,"ch":42}],"289":[{"g":41540,"x":903,"y":73,"hue":[-32,-42,-53],"cw":131,"ch":315}],"294":[{"g":34620,"x":-89,"y":389.5,"hue":[-74,-83,-97],"cx":-36,"cw":71,"ch":90},{"g":7162,"x":-84,"y":344.5,"hue":[-74,-83,-97],"cx":-31,"cw":74,"ch":98},{"g":41521,"x":54,"y":-14.5,"hue":[-69,-78,-90],"sx":-1,"cw":144,"ch":136},{"g":31317,"x":3,"y":282.5,"hue":[-57,-68,-82],"cw":109,"ch":187},{"g":34490,"x":38,"y":342.5,"hue":[-78,-92,-108],"cw":58,"ch":131}],"298":[{"g":36911,"x":431,"y":290.5,"hue":[-36,-47,-61],"sx":-1,"cw":102,"ch":173},{"g":34490,"x":392,"y":342.5,"hue":[-63,-77,-92],"sx":-1,"cw":58,"ch":131}],"302":[{"g":40915,"x":665,"y":97.5,"hue":[-10,-23,-36],"cw":95,"ch":223}],"303":[{"g":41521,"x":721,"y":-13.5,"hue":[-23,-31,-42],"cw":144,"ch":136}],"308":[{"g":40260,"x":42,"y":411,"hue":[-72,-87,-110],"sx":-1,"cw":86,"ch":86},{"g":30516,"x":-31,"y":382,"hue":[-66,-74,-98],"cw":63,"ch":65}],"309":[{"g":34490,"x":81,"y":364,"hue":[-74,-88,-102],"cw":58,"ch":131}],"312":[{"g":34490,"x":349,"y":364,"hue":[-57,-72,-87],"sx":-1,"cw":58,"ch":131},{"g":34700,"x":320,"y":427,"hue":[-16,-44,-80],"cw":20,"ch":37},{"g":11221,"x":343,"y":311,"hue":[-56,-78,-102],"cw":52,"ch":42}],"313":[{"g":10447,"x":442,"y":294,"hue":[-47,-68,-84],"sx":-1,"cw":46,"ch":70}],"317":[{"g":10447,"x":750,"y":49,"hue":[-48,-56,-59],"cw":46,"ch":70}],"322":[{"g":41521,"x":-32,"y":28.5,"hue":[-78,-86,-97],"sx":-1,"cw":144,"ch":136},{"g":700501,"x":-94,"y":435.5,"hue":[-65,-75,-90],"cw":110,"ch":87}],"323":[{"g":34490,"x":124,"y":385.5,"hue":[-67,-83,-98],"cw":58,"ch":131},{"g":34491,"x":92,"y":331.5,"hue":[-53,-63,-76],"cw":61,"ch":50}],"325":[{"g":34491,"x":347,"y":325.5,"hue":[-30,-43,-56],"sx":-1,"cw":61,"ch":50},{"g":34490,"x":306,"y":385.5,"hue":[-51,-67,-82],"sx":-1,"cw":58,"ch":131}],"332":[{"g":41521,"x":807,"y":29.5,"hue":[-28,-37,-47],"cw":144,"ch":136}],"333":[{"g":41540,"x":986,"y":244.5,"hue":[-50,-58,-67],"cw":131,"ch":315},{"g":41540,"x":989,"y":114.5,"hue":[-55,-64,-72],"cw":131,"ch":315},{"g":41517,"x":938,"y":319.5,"hue":[-32,-40,-51],"cw":61,"ch":203},{"g":41517,"x":938,"y":149.5,"hue":[-32,-40,-51],"cw":61,"ch":203},{"g":40498,"x":927,"y":463.5,"hue":[-32,-40,-51],"cw":71,"ch":66}],"336":[{"g":918,"x":-20,"y":485,"hue":[-49,-59,-72],"cw":44,"ch":35}],"338":[{"g":31316,"x":116,"y":337,"hue":[-48,-58,-70],"cw":86,"ch":197}],"339":[{"g":31316,"x":316,"y":336,"hue":[-24,-37,-51],"sx":-1,"cw":86,"ch":197}],"346":[{"g":10447,"x":831,"y":91,"hue":[-48,-56,-59],"cw":46,"ch":70}],"347":[{"g":41595,"x":922,"y":430,"hue":[-28,-41,-72],"cw":56,"ch":99}],"348":[{"g":41511,"x":1079,"y":493,"hue":[-39,-47,-58],"sx":-1,"cw":92,"ch":70}],"350":[{"g":30434,"x":-308,"y":-69.5,"hue":[-128,-128,-128],"cx":-255,"cy":-54,"cw":312,"ch":193}],"351":[{"g":40095,"x":220,"y":288.5,"hue":[-70,-79,-87],"sx":-1,"cw":201,"ch":117}],"352":[{"g":34534,"x":250,"y":330.5,"hue":[-42,-56,-72],"sx":-1,"cw":73,"ch":232},{"g":41577,"x":212,"y":407.5,"hue":[-8,-25,-42],"sx":-1,"cw":21,"ch":104},{"g":41577,"x":212,"y":369.5,"hue":[7,-12,-31],"sx":-1,"cw":21,"ch":104},{"g":41576,"x":238,"y":408.5,"hue":[-27,-41,-55],"sx":-1,"cw":19,"ch":104},{"g":41576,"x":238,"y":369.5,"hue":[-27,-41,-55],"sx":-1,"cw":19,"ch":104}],"361":[{"g":41521,"x":893,"y":72.5,"hue":[-40,-47,-57],"cw":144,"ch":136}],"362":[{"g":41540,"x":1072,"y":287.5,"hue":[-58,-65,-76],"cw":131,"ch":315},{"g":41540,"x":1072,"y":157.5,"hue":[-58,-65,-76],"cw":131,"ch":315}],"366":[{"g":40694,"x":209,"y":529,"hue":[-70,-84,-94],"sx":-1,"cw":47,"ch":35}],"367":[{"g":16168,"x":278,"y":483,"hue":[-55,-67,-95],"sx":-1,"cw":63,"ch":90},{"g":3566,"x":216,"y":432,"hue":[-29,-53,-78],"cw":34,"ch":139}],"371":[{"g":39940,"x":563,"y":485,"hue":[18,4,-10],"cw":149,"ch":99}],"375":[{"g":40915,"x":880,"y":203,"hue":[-49,-58,-70],"cw":95,"ch":223},{"g":10447,"x":912,"y":127,"hue":[-48,-56,-59],"cw":46,"ch":70}],"377":[{"g":41511,"x":1165,"y":536,"hue":[-55,-62,-72],"sx":-1,"cw":92,"ch":70}],"390":[{"g":34534,"x":1040,"y":373.5,"hue":[-81,-92,-121],"cw":73,"ch":232},{"g":41576,"x":1098,"y":452.5,"hue":[-51,-58,-69],"sx":-1,"cw":19,"ch":104},{"g":41576,"x":1098,"y":412.5,"hue":[-51,-58,-69],"sx":-1,"cw":19,"ch":104},{"g":41521,"x":979,"y":115.5,"hue":[-51,-58,-69],"cw":144,"ch":136}],"391":[{"g":41540,"x":1161,"y":330.5,"hue":[-74,-80,-90],"cw":131,"ch":315},{"g":41540,"x":1161,"y":200.5,"hue":[-74,-80,-90],"cw":131,"ch":315}],"404":[{"g":34490,"x":1037,"y":493,"hue":[-98,-109,-123],"sx":-1,"cw":58,"ch":131},{"g":31317,"x":1072,"y":433,"hue":[-71,-79,-92],"sx":-1,"cw":109,"ch":187}],"405":[{"g":37689,"x":1095,"y":582,"hue":[-76,-82,-107],"cw":51,"ch":36},{"g":41517,"x":1153,"y":427,"hue":[-72,-77,-87],"cw":61,"ch":203},{"g":41517,"x":1153,"y":257,"hue":[-72,-77,-87],"cw":61,"ch":203},{"g":40498,"x":1142,"y":571,"hue":[-72,-77,-87],"cw":71,"ch":66}],"410":[{"g":40475,"x":371,"y":534.5,"hue":[39,23,8],"cw":161,"ch":125},{"g":702252,"x":365,"y":598.5,"hue":[14,-6,-36],"cw":47,"ch":44},{"g":32829,"x":441,"y":524.5,"hue":[37,17,-17],"sx":-1,"cw":37,"ch":44},{"g":32846,"x":466,"y":545.5,"hue":[37,17,-17],"sx":-1,"cw":46,"ch":33}],"411":[{"g":29283,"x":461,"y":539.5,"hue":[39,19,-15],"cw":49,"ch":51},{"g":926,"x":456,"y":574.5,"hue":[39,19,-15],"cw":50,"ch":37},{"look":1882,"x":482,"y":565.5,"hue":[0,0,0],"anim":1}],"417":[{"g":34490,"x":994,"y":514.5,"hue":[-94,-105,-119],"sx":-1,"cw":58,"ch":131}],"419":[{"g":702252,"x":1139,"y":598.5,"hue":[-72,-80,-104],"cw":47,"ch":44},{"g":39070,"x":1148,"y":505.5,"hue":[-73,-88,-120],"cw":56,"ch":59},{"g":41521,"x":1065,"y":158.5,"hue":[-61,-67,-78],"cw":144,"ch":136},{"g":41511,"x":1294,"y":600.5,"hue":[-74,-79,-89],"sx":-1,"cw":92,"ch":70}],"420":[{"g":40538,"x":-125,"y":464,"hue":[-128,-128,-128],"cw":179,"ch":189}],"425":[{"g":702252,"x":408,"y":620,"hue":[13,-6,-36],"cw":47,"ch":44}],"431":[{"g":34490,"x":951,"y":536,"hue":[-88,-100,-115],"sx":-1,"cw":58,"ch":131},{"g":34491,"x":983,"y":482,"hue":[-64,-73,-85],"sx":-1,"cw":61,"ch":50}],"444":[{"g":31316,"x":953,"y":490.5,"hue":[-60,-69,-83],"sx":-1,"cw":86,"ch":197},{"g":40095,"x":863,"y":439.5,"hue":[-87,-93,-102],"cw":201,"ch":117}],"447":[{"g":41521,"x":1151,"y":201.5,"hue":[-77,-82,-92],"cw":144,"ch":136}],"454":[{"g":40475,"x":500,"y":599,"hue":[20,6,-8],"cw":161,"ch":125},{"g":40698,"x":520,"y":606,"hue":[18,0,-33],"cw":64,"ch":41},{"g":30531,"x":513,"y":629,"hue":[18,0,-33],"cw":61,"ch":68}],"455":[{"g":36904,"x":626,"y":625,"hue":[16,-2,-35],"sx":-1,"cw":42,"ch":32},{"g":32937,"x":620,"y":613,"hue":[16,-2,-35],"cw":25,"ch":53}],"458":[{"g":36911,"x":899,"y":529,"hue":[-57,-65,-78],"sx":-1,"cw":102,"ch":173},{"g":34490,"x":865,"y":579,"hue":[-69,-82,-98],"sx":-1,"cw":58,"ch":131}],"463":[{"g":40538,"x":4,"y":528.5,"hue":[-128,-128,-128],"cw":179,"ch":189}],"468":[{"g":702252,"x":537,"y":684.5,"hue":[-12,-30,-59],"cw":47,"ch":44}],"471":[{"g":34490,"x":822,"y":600.5,"hue":[-62,-76,-92],"sx":-1,"cw":58,"ch":131}],"472":[{"g":10447,"x":915,"y":530.5,"hue":[-68,-86,-104],"sx":-1,"cw":46,"ch":70}],"474":[{"g":20317,"x":1119,"y":670.5,"hue":[-76,-87,-113],"sx":-1,"cw":95,"ch":60},{"g":39077,"x":1087,"y":717.5,"hue":[-58,-70,-86],"sx":-1,"cw":27,"ch":26}],"475":[],"485":[{"g":34491,"x":816,"y":564,"hue":[-54,-63,-75],"sx":-1,"cw":61,"ch":50},{"g":34490,"x":779,"y":622,"hue":[-54,-69,-84],"sx":-1,"cw":58,"ch":131}],"489":[{"g":702252,"x":1096,"y":706,"hue":[-74,-85,-110],"cw":47,"ch":44}],"498":[{"g":31316,"x":787,"y":573.5,"hue":[-48,-58,-70],"sx":-1,"cw":86,"ch":197}],"501":[{"g":702252,"x":967,"y":727.5,"hue":[-67,-79,-105],"cw":47,"ch":44}],"503":[{"g":37260,"x":1091,"y":446.5,"hue":[-51,-70,-88],"cw":123,"ch":150}],"512":[{"g":34534,"x":653,"y":567,"hue":[-38,-50,-80],"cw":73,"ch":232},{"g":41576,"x":665,"y":644,"hue":[-10,-22,-34],"cw":19,"ch":104},{"g":41576,"x":665,"y":606,"hue":[-10,-22,-34],"cw":19,"ch":104}],"517":[{"g":4269,"x":1128,"y":310,"hue":[-128,-128,-128],"cw":26,"ch":171}],"525":[{"g":700501,"x":594,"y":736.5,"hue":[-40,-53,-70],"cw":110,"ch":87}],"526":[{"g":34490,"x":726,"y":686.5,"hue":[-74,-87,-102],"cw":58,"ch":131},{"g":31317,"x":691,"y":626.5,"hue":[-47,-57,-71],"cw":109,"ch":187}],"535":[{"g":40537,"x":143,"y":651,"hue":[-128,-128,-128],"cw":165,"ch":180}],"540":[{"g":344,"x":664,"y":762,"hue":[-45,-53,-62],"cw":41,"ch":63},{"g":16168,"x":661,"y":741,"hue":[-50,-59,-78],"cw":63,"ch":90}],"541":[{"g":34490,"x":769,"y":708,"hue":[-81,-92,-108],"cw":58,"ch":131}],"544":[{"g":18011,"x":993,"y":791,"hue":[-59,-67,-78],"cw":81,"ch":48}],"560":[{"g":34490,"x":812,"y":729.5,"hue":[-87,-98,-110],"cw":58,"ch":131},{"g":34491,"x":780,"y":675.5,"hue":[-54,-62,-75],"cw":61,"ch":50},{"g":700503,"x":1046,"y":765.5,"hue":[-65,-80,-102],"sx":-1,"cw":116,"ch":85},{"g":18011,"x":735,"y":833.5,"hue":[-80,-84,-91],"cw":81,"ch":48},{"g":31316,"x":804,"y":680.5,"hue":[-59,-68,-80],"cw":86,"ch":197},{"g":40260,"x":904,"y":797.5,"hue":[-75,-89,-109],"cw":86,"ch":86},{"g":40538,"x":261,"y":708.5,"hue":[-128,-128,-128],"cw":179,"ch":189},{"g":40095,"x":908,"y":632.5,"hue":[-65,-73,-84],"sx":-1,"cw":201,"ch":117},{"g":34534,"x":868,"y":674.5,"hue":[-65,-77,-109],"cw":73,"ch":232},{"g":41576,"x":880,"y":751.5,"hue":[-48,-56,-67],"cw":19,"ch":104},{"g":41576,"x":880,"y":713.5,"hue":[-48,-56,-67],"cw":19,"ch":104},{"g":41577,"x":906,"y":752.5,"hue":[-48,-56,-67],"cw":21,"ch":104},{"g":41577,"x":906,"y":713.5,"hue":[-48,-56,-67],"cw":21,"ch":104},{"g":40537,"x":401,"y":729.5,"hue":[-128,-128,-128],"cw":165,"ch":180},{"g":31745,"x":-85,"y":-24.5,"hue":[0,0,0],"cx":-32,"cy":-9,"cw":1267,"ch":866},{"g":40547,"x":364,"y":685.5,"hue":[-128,-128,-128],"cw":163,"ch":165},{"g":40538,"x":520,"y":786.5,"hue":[-128,-128,-128],"cw":179,"ch":189},{"g":32251,"x":1053.5,"y":186.5,"hue":[-127,-127,-127],"rotation":0.881216739331937,"cx":253.5,"cy":65.5,"cw":507,"ch":131},{"g":700967,"x":525,"y":-158,"hue":[-127,-127,-127],"sx":1.5,"sy":1.5,"cx":244,"cy":-95,"cw":488,"ch":62},{"g":36829,"x":624,"y":53,"hue":[0,0,0],"sx":-1.5,"sy":1.5,"alpha":0.48627450980392156,"cx":394,"cy":46,"cw":805,"ch":438},{"g":27479,"x":450.5,"y":560.5,"hue":[5,-40,-127],"sx":0.741,"sy":0.903,"alpha":0.48627450980392156,"cx":373.5,"cy":247.5,"cw":747,"ch":495},{"g":30902,"x":1077.5,"y":549,"hue":[0,0,0],"sx":-1,"sy":1.158,"cx":174.5,"cy":488,"cw":507,"ch":845},{"g":30902,"x":121.5,"y":396,"hue":[0,0,0],"sy":1.275,"cx":174.5,"cy":488,"cw":507,"ch":845}]},"atlasLayout":{"width":1879,"height":681,"graphicsPositions":{"344":{"sx":1449,"sy":596,"sw":41,"sh":63},"918":{"sx":1834,"sy":316,"sw":44,"sh":35},"926":{"sx":1302,"sy":142,"sw":50,"sh":37},"3566":{"sx":1302,"sy":1,"sw":34,"sh":139},"4269":{"sx":1789,"sy":372,"sw":26,"sh":171},"7162":{"sx":1740,"sy":200,"sw":74,"sh":98,"cx":31},"7945":{"sx":921,"sy":607,"sw":71,"sh":64},"10447":{"sx":1135,"sy":183,"sw":46,"sh":70},"11221":{"sx":1135,"sy":255,"sw":52,"sh":42},"16168":{"sx":1830,"sy":485,"sw":46,"sh":65,"cw":63,"ch":90},"18011":{"sx":1649,"sy":630,"sw":81,"sh":48},"20317":{"sx":824,"sy":607,"sw":95,"sh":60},"27479":{"sx":1335,"sy":596,"sw":112,"sh":74,"cw":747,"ch":495},"29283":{"sx":1540,"sy":309,"sw":49,"sh":51},"30434":{"sx":510,"sy":441,"sw":312,"sh":193,"cx":255,"cy":54},"30516":{"sx":1767,"sy":615,"sw":63,"sh":65},"30531":{"sx":1767,"sy":545,"sw":61,"sh":68},"30902":{"sx":808,"sy":1,"sw":192,"sh":321,"cx":158,"cy":11,"cw":507,"ch":845},"31316":{"sx":1654,"sy":1,"sw":86,"sh":197},"31317":{"sx":1224,"sy":469,"sw":109,"sh":187},"31745":{"sx":1010,"sy":509,"sw":212,"sh":145,"cx":32,"cy":9,"cw":1267,"ch":866},"32251":{"sx":1,"sy":441,"sw":507,"sh":131},"32829":{"sx":1743,"sy":494,"sw":37,"sh":44},"32846":{"sx":1594,"sy":644,"sw":46,"sh":33},"32937":{"sx":1356,"sy":226,"sw":25,"sh":53},"34490":{"sx":1578,"sy":1,"sw":58,"sh":131},"34491":{"sx":1817,"sy":433,"sw":61,"sh":50},"34534":{"sx":1602,"sy":309,"sw":73,"sh":232},"34620":{"sx":1742,"sy":1,"sw":71,"sh":90,"cx":36},"34700":{"sx":1191,"sy":469,"sw":20,"sh":37},"36829":{"sx":1,"sy":1,"sw":805,"sh":438,"cx":17,"cy":346},"36904":{"sx":1832,"sy":598,"sw":42,"sh":32},"36911":{"sx":1498,"sy":364,"sw":102,"sh":173},"37260":{"sx":1453,"sy":1,"sw":123,"sh":150},"37689":{"sx":1492,"sy":644,"sw":51,"sh":36},"39070":{"sx":1817,"sy":372,"sw":56,"sh":59},"39077":{"sx":1740,"sy":372,"sw":27,"sh":26},"39940":{"sx":1498,"sy":543,"sw":149,"sh":99},"40095":{"sx":1191,"sy":350,"sw":201,"sh":117},"40260":{"sx":1394,"sy":364,"sw":86,"sh":86},"40475":{"sx":1335,"sy":469,"sw":161,"sh":125},"40498":{"sx":1453,"sy":153,"sw":71,"sh":66},"40537":{"sx":1135,"sy":1,"sw":165,"sh":180},"40538":{"sx":1010,"sy":318,"sw":179,"sh":189},"40547":{"sx":1191,"sy":183,"sw":163,"sh":165},"40694":{"sx":1545,"sy":644,"sw":47,"sh":35},"40698":{"sx":1677,"sy":494,"sw":64,"sh":41},"40915":{"sx":1356,"sy":1,"sw":95,"sh":223},"40920":{"sx":1540,"sy":153,"sw":112,"sh":154},"41511":{"sx":1740,"sy":300,"sw":92,"sh":70},"41517":{"sx":1677,"sy":200,"sw":61,"sh":203},"41521":{"sx":1394,"sy":226,"sw":144,"sh":136},"41539":{"sx":1834,"sy":1,"sw":10,"sh":313},"41540":{"sx":1002,"sy":1,"sw":131,"sh":315},"41576":{"sx":1800,"sy":93,"sw":19,"sh":104},"41577":{"sx":1654,"sy":200,"sw":21,"sh":104},"41595":{"sx":1742,"sy":93,"sw":56,"sh":99},"41605":{"sx":824,"sy":324,"sw":184,"sh":281},"700501":{"sx":1677,"sy":405,"sw":110,"sh":87},"700503":{"sx":1649,"sy":543,"sw":116,"sh":85},"700967":{"sx":1,"sy":574,"sw":488,"sh":62,"cy":252},"702252":{"sx":1830,"sy":552,"sw":47,"sh":44}}}}