{"id":13597,"topNeighbourId":13598,"bottomNeighbourId":13596,"leftNeighbourId":13085,"rightNeighbourId":14109,"shadowBonusOnEntities":-1,"cells":[{"l":67,"c":24},{"l":67,"c":-128},{"l":67,"c":-32},{"l":3,"c":-32},{"l":67,"c":-32},{"l":67,"c":-32},{"l":67,"c":-32},{"l":67,"c":-32},{"l":67,"c":-32},{"l":67,"c":-32},{"l":67,"c":-32},{"l":67,"c":-32},{"l":67,"c":-32},{"l":67,"c":-32},{"l":67,"c":16},{"l":67,"c":64},{"l":67,"c":64},{"l":67,"c":64},{"l":67,"c":64},{"l":67,"c":64},{"l":67,"c":64},{"l":67,"c":64},{"l":67,"c":64},{"l":3,"c":64},{"l":67,"c":64},{"l":67,"c":64},{"l":67,"c":64},{"l":67,"c":-61},{"l":67,"c":56},{"l":3},{"l":67},{"l":3},{"l":67},{"l":67},{"l":67},{"l":67},{"l":67},{"l":67},{"l":67},{"l":67},{"l":67},{"l":67,"c":1},{"l":3,"c":16},{"l":3},{"l":67},{"l":3},{"l":67},{"l":67},{"l":67},{"l":67},{"l":67},{"l":3},{"l":67},{"l":67},{"l":67},{"l":67,"c":-125},{"l":67,"c":40},{},{"l":3},{"l":3},{"l":67},{"l":67},{"l":67},{"l":67},{"l":67},{"l":67},{"l":67},{"l":67},{"l":67},{"l":67,"c":1},{"l":3,"c":16},{},{"l":3},{"l":3},{"l":67},{"l":67},{"l":67},{"l":67},{"l":67},{"l":3},{"l":67},{"l":67},{"l":67},{"l":67,"c":-125},{"l":3,"c":56},{"l":67},{"l":3},{"l":3},{"l":67},{"l":67},{"l":67},{"l":67},{"l":67},{"l":67},{"l":67},{"l":67},{"l":67},{"l":67,"c":1},{"l":3,"c":16},{"l":67},{"l":67},{"l":67},{"l":67},{"l":67},{"l":67},{"l":67},{"l":67},{"l":3},{"l":67},{"l":67},{"l":67},{"l":67,"c":-125},{"l":3,"c":56},{"l":67},{"l":3},{"l":3},{"l":67},{"l":67},{"l":67},{"l":67},{"l":67},{"l":3},{"l":67},{"l":67},{"l":3},{"l":3,"c":1},{"l":3},{"l":67},{"l":67},{"l":66},{"l":67},{"l":67},{"l":67},{"l":3},{"l":3},{},{"l":67},{"l":67},{"l":67},{"l":67,"c":-125},{},{"l":3},{"l":3},{"l":2},{"l":66},{"l":67},{"l":67},{"l":67},{"l":67},{"l":3},{"l":67},{"l":67},{"l":67},{"l":67,"c":1},{},{"l":67},{"l":66},{"l":66},{"l":66},{"l":67},{"l":67},{},{"l":3},{"l":3},{"l":67},{"l":67},{"l":67},{"l":67,"c":-128},{},{"l":2},{},{"l":2},{"l":66},{"l":3},{"l":67},{"l":2},{"l":67},{},{"l":2},{"l":67},{"l":67},{"l":67},{"l":2},{"l":67},{"l":66},{"l":66},{"l":66},{"l":67},{"l":67},{"l":67},{},{},{"l":67},{"l":3},{"l":67},{"l":66},{"l":67,"c":56},{"l":67},{"l":66},{"l":2},{"l":66},{},{"l":67},{"l":67},{"l":67},{},{"l":66},{"l":67},{"l":3},{"l":67},{"l":67,"c":16},{"l":67},{"l":66},{"l":66},{"l":66},{"l":2},{"l":3},{"l":67},{"l":66},{"l":66},{"l":67},{"l":67},{"l":3},{"l":66},{"l":67,"c":56},{"l":67},{"l":66},{"l":2},{"l":66},{"l":66},{"l":67},{"l":67},{"l":66},{"l":66},{"l":66},{"l":67},{"l":3},{"l":67},{"l":67,"c":16},{"l":67},{"l":66},{"l":66},{"l":66},{"l":67},{"l":3},{"l":67},{"l":66},{"l":66},{"l":66},{"l":67},{"l":3},{"l":67,"c":2},{"l":3,"c":56},{"l":3},{"l":3},{"l":2},{"l":66},{"l":67},{"l":67},{"l":3},{"l":66},{"l":66},{"l":66},{"l":66},{"l":3},{"l":3,"c":1},{"l":3,"c":16},{"l":67},{"l":64},{"l":2},{"l":67},{"l":67},{"l":3},{"l":66},{"l":66},{"l":66},{"l":66},{"l":2},{"l":3},{"l":67,"c":-125},{"l":67,"c":56},{"l":3},{"l":67},{},{"l":67},{"l":67},{"l":67},{"l":3},{"l":66},{"l":2},{"l":66},{"l":66},{"l":2},{"l":67,"c":1},{"l":3,"c":16},{"l":67},{"l":67},{"l":67},{"l":67},{"l":67},{"l":3},{"l":66},{"l":66},{"l":66},{"l":66},{"l":66},{"l":3},{"l":67,"c":-125},{"l":67,"c":56},{"l":3},{"l":67},{"l":67},{"l":67},{"l":67},{"l":67},{"l":67},{"l":66},{"l":66},{"l":66},{"l":66},{"l":3},{"l":67,"c":1},{"l":67,"c":16},{"l":67},{"l":67},{"l":67},{"l":67},{"l":66},{},{"l":67},{"l":66},{"l":66},{"l":66},{"l":66},{"l":3},{"l":67,"c":-125},{"l":67,"c":56},{"l":3},{"l":67},{"l":67},{"l":67},{"l":66},{"l":66},{"l":64},{"l":67},{"l":66},{"l":66},{"l":66},{"l":3},{"l":67,"c":1},{"l":3,"c":16},{"l":67},{"l":67},{"l":3},{"l":66},{"l":66},{"l":66},{"l":67},{"l":67},{"l":66},{"l":66},{"l":67},{"l":3},{"l":67,"c":-125},{"l":67,"c":56},{"l":3},{"l":67},{"l":3},{"l":2},{"l":66},{"l":66},{"l":67},{"l":67},{"l":67},{"l":66},{"l":67},{"l":3},{"l":67,"c":1},{"l":67,"c":16},{"l":67},{"l":67},{},{"l":66},{"l":66},{"l":66},{"l":67},{"l":67},{"l":67},{"l":67},{"l":67},{"l":3},{"l":67,"c":-125},{"l":67,"c":56},{"l":3},{"l":67},{"l":2},{"l":2},{"l":66},{"l":66},{"l":3},{"l":67},{"l":67},{"l":67},{"l":67},{"l":3},{"l":67,"c":1},{"l":67,"c":16},{"l":67},{"l":67},{"l":67},{"l":66},{"l":66},{"l":66},{"l":67},{"l":67},{"l":67},{"l":67},{"l":67},{"l":3},{"l":67,"c":-128},{"l":67,"c":56},{"l":3},{"l":67},{"l":67},{"l":66},{"l":66},{"l":66},{"l":2},{"l":67},{"l":67},{"l":67},{"l":67},{"l":3},{"l":67},{"l":3,"c":16},{"l":67},{"l":67},{"l":67},{"l":66},{"l":66},{"l":66},{"l":67},{"l":67},{"l":67},{"l":67},{"l":67},{"l":3},{"l":66},{"l":67,"c":56},{},{"l":67},{"l":67},{"l":67},{"l":66},{"l":66},{},{"l":67},{"l":67},{"l":67},{"l":67},{"l":3},{"l":66},{"l":3,"c":16},{"l":67},{"l":67},{"l":67},{"l":67},{"l":66},{"l":67},{"l":67},{"l":67},{"l":67},{"l":67},{"l":67},{},{"l":66},{"l":67,"c":56},{"l":67},{"l":67},{"l":67},{"l":67},{"l":67},{"l":67},{"l":67},{"l":67},{"l":67},{"l":67},{"l":67},{},{"l":66},{},{"l":67},{"l":67},{"l":67},{"l":67},{"l":67},{"l":67},{"l":67},{"l":67},{"l":67},{"l":67},{"l":67},{"l":66},{"l":66},{"l":67,"c":56},{"l":67},{"l":67},{"l":67},{"l":67},{"l":67},{"l":67},{"l":67},{"l":67},{"l":67},{"l":67},{"l":67},{"l":67},{"l":66},{"l":67,"c":16},{"l":67},{"l":67},{"l":67},{"l":67},{"l":67},{"l":67},{"l":67},{"l":67},{"l":67},{"l":67},{"l":67},{"l":66},{"l":66},{"l":67,"c":60},{"l":67,"c":4},{"l":67,"c":4},{"l":67,"c":4},{"l":67,"c":4},{"l":67,"c":4},{"l":67,"c":4},{"l":67,"c":4},{"l":67,"c":4},{"l":67,"c":4},{"l":67,"c":4},{"l":67,"c":4},{"l":67,"c":4},{"l":66},{"l":67,"c":14},{"l":67,"c":14},{"l":67,"c":14},{"l":67,"c":14},{"l":67,"c":14},{"l":67,"c":14},{"l":67,"c":14},{"l":67,"c":14},{"l":67,"c":14},{"l":67,"c":14},{"l":67,"c":14},{"l":67,"c":14},{"l":67,"c":14},{"l":66}],"midgroundLayer":{"0":[{"g":16115,"x":-104,"y":-825,"hue":[15,15,15],"cx":-8,"cy":-101,"cw":222,"ch":723},{"g":9487,"x":-41,"y":-20,"hue":[0,0,0],"cy":-5,"cw":183,"ch":138}],"1":[{"g":16108,"x":110,"y":-58,"hue":[15,15,15],"sx":-1,"cw":25,"ch":58}],"47":[{"g":16105,"x":509,"y":9.5,"hue":[18,18,18],"sx":-1,"cw":25,"ch":58}],"56":[{"g":16142,"x":-120,"y":29,"hue":[13,13,13],"cw":93,"ch":85}],"57":[{"g":16141,"x":34,"y":14,"hue":[15,15,15],"cw":119,"ch":98}],"60":[{"g":16914,"x":357,"y":80,"hue":[17,17,17],"cw":17,"ch":14},{"g":17050,"x":321,"y":54,"hue":[17,17,17],"cw":56,"ch":33}],"61":[{"g":16104,"x":462,"y":13,"hue":[18,18,18],"sx":-1,"cw":52,"ch":73}],"71":[{"g":16142,"x":95,"y":50.5,"hue":[15,15,15],"cw":93,"ch":85}],"84":[],"97":[{"g":17049,"x":1082,"y":111,"hue":[5,5,5],"cw":82,"ch":33}],"101":[{"g":16107,"x":257,"y":82.5,"hue":[17,17,17],"cw":52,"ch":73}],"104":[{"g":17049,"x":523,"y":132.5,"hue":[19,19,19],"cw":82,"ch":33}],"108":[{"g":16913,"x":881,"y":140.5,"hue":[15,15,15],"cw":25,"ch":18}],"113":[{"g":16106,"x":42,"y":54,"hue":[14,14,14],"cw":51,"ch":120}],"114":[{"g":16105,"x":208,"y":117,"hue":[14,14,14],"sx":-1,"cw":25,"ch":58}],"116":[{"g":16914,"x":357,"y":166,"hue":[-16,-16,-16],"cw":17,"ch":14}],"123":[{"g":16106,"x":990,"y":54,"hue":[11,11,11],"sx":-1,"cw":51,"ch":120}],"127":[{"g":16108,"x":105,"y":135.5,"hue":[13,13,13],"cw":25,"ch":58}],"135":[{"g":16117,"x":740,"y":-482.5,"hue":[18,18,18],"cw":230,"ch":700}],"139":[{"g":16107,"x":1203,"y":125.5,"hue":[6,6,6],"cw":52,"ch":73}],"144":[{"g":17050,"x":321,"y":183,"hue":[18,18,18],"cw":56,"ch":33}],"155":[{"g":16914,"x":142,"y":230.5,"hue":[7,7,7],"cw":17,"ch":14}],"158":[{"g":16103,"x":431,"y":117.5,"hue":[19,19,19],"sx":-1,"cw":51,"ch":120}],"161":[{"g":16141,"x":593,"y":164.5,"hue":[20,20,20],"cw":119,"ch":98}],"164":[{"g":16105,"x":880,"y":174.5,"hue":[16,16,16],"cw":25,"ch":58}],"168":[{"g":16139,"x":-58,"y":106,"hue":[1,1,1],"cw":147,"ch":166}],"169":[{"g":16973,"x":47,"y":221,"hue":[6,6,6],"cw":85,"ch":65}],"170":[{"g":16120,"x":79,"y":-1,"hue":[12,12,12],"cw":163,"ch":276}],"173":[{"g":16107,"x":474,"y":190,"hue":[20,20,20],"sx":-1,"cw":52,"ch":73}],"175":[{"g":16131,"x":659,"y":226,"hue":[20,20,20],"sx":-1,"cw":82,"ch":53}],"176":[{"g":16106,"x":732,"y":140,"hue":[20,20,20],"sx":-1,"cw":51,"ch":120}],"177":[{"g":16116,"x":657,"y":-406,"hue":[19,19,19],"cw":252,"ch":685}],"178":[{"g":16132,"x":899,"y":231,"hue":[17,17,17],"sx":-1,"cw":78,"ch":54}],"182":[{"g":17054,"x":-2,"y":244.5,"hue":[2,2,2],"cw":78,"ch":56}],"189":[{"g":16104,"x":613,"y":206.5,"hue":[20,20,20],"cw":52,"ch":73}],"191":[{"g":16121,"x":742,"y":122.5,"hue":[18,18,18],"cw":195,"ch":178}],"192":[{"g":17060,"x":890,"y":252.5,"hue":[16,16,16],"cw":50,"ch":32}],"196":[{"g":7715,"x":-109,"y":206,"hue":[4,4,4],"cw":201,"ch":106},{"g":16108,"x":24,"y":243,"hue":[4,4,4],"sx":-1,"cw":25,"ch":58}],"201":[{"g":16142,"x":396,"y":244,"hue":[20,20,20],"cw":93,"ch":85}],"205":[{"g":16139,"x":716,"y":149,"hue":[19,19,19],"cw":147,"ch":166}],"206":[{"g":16135,"x":817,"y":256,"hue":[17,17,17],"cw":75,"ch":57}],"215":[{"g":17054,"x":428,"y":287.5,"hue":[20,20,20],"cw":78,"ch":56}],"218":[{"g":7715,"x":622,"y":227.5,"hue":[0,0,0],"cw":201,"ch":106}],"220":[{"g":17057,"x":861,"y":288.5,"hue":[16,16,16],"cw":75,"ch":45}],"226":[{"g":7715,"x":63,"y":249,"hue":[0,0,0],"cw":201,"ch":106}],"241":[{"g":16073,"x":268,"y":350.5,"hue":[20,20,20],"cw":60,"ch":31}],"254":[{"g":17051,"x":117,"y":365,"hue":[19,19,19],"cw":82,"ch":42}],"261":[{"g":16070,"x":736,"y":365,"hue":[18,18,18],"cw":87,"ch":59}],"268":[{"g":16119,"x":146,"y":157.5,"hue":[20,20,20],"cw":107,"ch":265}],"269":[{"g":16132,"x":261,"y":378.5,"hue":[17,17,17],"cw":78,"ch":54}],"275":[{"g":16073,"x":784,"y":393.5,"hue":[17,17,17],"cw":60,"ch":31}],"279":[{"g":16103,"x":1203,"y":289.5,"hue":[7,7,7],"cw":51,"ch":120}],"283":[{"g":16114,"x":150,"y":-307,"hue":[18,18,18],"cw":255,"ch":757}],"284":[{"g":16104,"x":376,"y":357,"hue":[18,18,18],"sx":-1,"cw":52,"ch":73}],"289":[{"g":16077,"x":696,"y":399,"hue":[17,17,17],"cw":118,"ch":72}],"290":[{"g":16083,"x":801,"y":400,"hue":[15,15,15],"cw":102,"ch":69}],"296":[{"g":16107,"x":171,"y":383.5,"hue":[20,20,20],"cw":52,"ch":73}],"306":[{"g":17050,"x":1052,"y":419.5,"hue":[7,7,7],"cw":56,"ch":33}],"307":[],"328":[{"g":16120,"x":466,"y":235.5,"hue":[17,17,17],"cw":163,"ch":276}],"343":[{"g":16119,"x":533,"y":265,"hue":[17,17,17],"cw":107,"ch":265}],"344":[{"g":17051,"x":633,"y":494,"hue":[17,17,17],"cw":82,"ch":42}],"358":[{"g":17059,"x":698,"y":530.5,"hue":[-16,-16,-16],"cw":26,"ch":15}],"366":[{"g":16913,"x":150,"y":549,"hue":[20,20,20],"cw":25,"ch":18}],"367":[{"g":17049,"x":222,"y":541,"hue":[18,18,18],"cw":82,"ch":33}],"368":[{"g":17055,"x":299,"y":514,"hue":[16,16,16],"cw":82,"ch":71}],"373":[{"g":16105,"x":751,"y":497,"hue":[17,17,17],"cw":25,"ch":58}],"375":[{"g":16914,"x":959,"y":553,"hue":[14,14,14],"cw":17,"ch":14}],"381":[{"g":16141,"x":249,"y":508.5,"hue":[15,15,15],"cw":119,"ch":98}],"383":[{"g":16082,"x":444,"y":560.5,"hue":[16,16,16],"cw":73,"ch":39}],"387":[{"g":16104,"x":785,"y":507.5,"hue":[16,16,16],"cw":52,"ch":73}],"389":[{"g":17062,"x":965,"y":566.5,"hue":[13,13,13],"cw":29,"ch":19}],"395":[{"g":16135,"x":222,"y":567,"hue":[18,18,18],"cw":75,"ch":57}],"396":[{"g":16131,"x":285,"y":569,"hue":[15,15,15],"cw":82,"ch":53}],"409":[{"g":7715,"x":192,"y":528.5,"hue":[0,0,0],"cw":201,"ch":106}],"423":[{"g":16914,"x":271,"y":639,"hue":[17,17,17],"cw":17,"ch":14}],"427":[{"g":17054,"x":557,"y":610,"hue":[16,16,16],"cw":78,"ch":56}],"439":[{"g":16068,"x":435,"y":634.5,"hue":[14,14,14],"cw":92,"ch":63}],"445":[{"g":16103,"x":1033,"y":547.5,"hue":[13,13,13],"sx":-1,"cw":51,"ch":120}],"449":[{"g":17054,"x":41,"y":653,"hue":[17,17,17],"cw":78,"ch":56},{"g":16115,"x":-61,"y":-116,"hue":[17,17,17],"cx":-8,"cy":-101,"cw":222,"ch":723}],"452":[{"g":16104,"x":312,"y":615,"hue":[9,9,9],"cw":52,"ch":73}],"455":[{"g":16121,"x":527,"y":531,"hue":[15,15,15],"cw":195,"ch":178}],"459":[{"g":17049,"x":910,"y":670,"hue":[14,14,14],"cw":82,"ch":33}],"466":[{"g":16105,"x":364,"y":647.5,"hue":[11,11,11],"cw":25,"ch":58}],"468":[{"g":16913,"x":537,"y":699.5,"hue":[15,15,15],"cw":25,"ch":18}],"474":[{"g":16117,"x":998,"y":33.5,"hue":[7,7,7],"cw":230,"ch":700}],"477":[{"g":16104,"x":118,"y":658,"hue":[10,10,10],"sx":-1,"cw":52,"ch":73}],"480":[{"g":17051,"x":289,"y":709,"hue":[8,8,8],"cw":82,"ch":42}],"481":[{"g":17049,"x":394,"y":713,"hue":[13,13,13],"cw":82,"ch":33}],"488":[{"g":16114,"x":924,"y":-6,"hue":[12,12,12],"cw":255,"ch":757}],"490":[{"g":16116,"x":-74,"y":88.5,"hue":[4,4,4],"cw":252,"ch":685}],"491":[{"g":16104,"x":161,"y":679.5,"hue":[4,4,4],"sx":-1,"cw":52,"ch":73}],"496":[{"g":16106,"x":603,"y":634.5,"hue":[13,13,13],"sx":-1,"cw":51,"ch":120}],"501":[{"g":16108,"x":965,"y":694.5,"hue":[13,13,13],"cw":25,"ch":58}],"502":[{"g":7715,"x":966,"y":657.5,"hue":[0,0,0],"cw":201,"ch":106}],"530":[{"g":16104,"x":1043,"y":722.5,"hue":[7,7,7],"cw":52,"ch":73}],"533":[{"g":16107,"x":130,"y":749,"hue":[3,3,3],"sx":-1,"cw":52,"ch":73}],"560":[{"g":16104,"x":634,"y":829.5,"hue":[4,4,4],"sx":-1,"cw":52,"ch":73},{"g":16104,"x":1150,"y":829.5,"hue":[6,6,6],"sx":-1,"cw":52,"ch":73},{"g":16103,"x":85,"y":805.5,"hue":[1,1,1],"cw":51,"ch":120},{"g":16103,"x":1119,"y":805.5,"hue":[7,7,7],"sx":-1,"cw":51,"ch":120},{"g":16118,"x":232,"y":652.5,"hue":[2,2,2],"cw":127,"ch":198},{"g":16118,"x":920,"y":824.5,"hue":[8,8,8],"cw":127,"ch":198}]},"atlasLayout":{"width":1312,"height":784,"graphicsPositions":{"7715":{"sx":1269,"sy":398,"sw":30,"sh":16,"cw":201,"ch":106},"9487":{"sx":692,"sy":703,"sw":27,"sh":21,"cy":5,"cw":183,"ch":138},"16068":{"sx":258,"sy":688,"sw":92,"sh":63},"16070":{"sx":439,"sy":703,"sw":87,"sh":59},"16073":{"sx":1169,"sy":744,"sw":60,"sh":31},"16077":{"sx":1077,"sy":659,"sw":118,"sh":72},"16082":{"sx":1010,"sy":733,"sw":73,"sh":39},"16083":{"sx":1165,"sy":356,"sw":102,"sh":69},"16103":{"sx":1206,"sy":427,"sw":51,"sh":120},"16104":{"sx":1254,"sy":169,"sw":52,"sh":73},"16105":{"sx":1269,"sy":338,"sw":25,"sh":58},"16106":{"sx":1206,"sy":549,"sw":51,"sh":120},"16107":{"sx":1259,"sy":427,"sw":52,"sh":73},"16108":{"sx":1260,"sy":278,"sw":25,"sh":58},"16114":{"sx":1,"sy":1,"sw":255,"sh":757},"16115":{"sx":744,"sy":1,"sw":222,"sh":723,"cx":8,"cy":101},"16116":{"sx":258,"sy":1,"sw":252,"sh":685},"16117":{"sx":512,"sy":1,"sw":230,"sh":700},"16118":{"sx":1077,"sy":459,"sw":127,"sh":198},"16119":{"sx":968,"sy":459,"sw":107,"sh":265},"16120":{"sx":968,"sy":1,"sw":163,"sh":276},"16121":{"sx":968,"sy":279,"sw":195,"sh":178},"16131":{"sx":608,"sy":703,"sw":82,"sh":53},"16132":{"sx":769,"sy":726,"sw":78,"sh":54},"16135":{"sx":692,"sy":726,"sw":75,"sh":57},"16139":{"sx":1133,"sy":1,"sw":147,"sh":166},"16141":{"sx":1133,"sy":169,"sw":119,"sh":98},"16142":{"sx":1165,"sy":269,"sw":93,"sh":85},"16913":{"sx":608,"sy":758,"sw":25,"sh":18},"16914":{"sx":721,"sy":703,"sw":17,"sh":14},"16973":{"sx":352,"sy":688,"sw":85,"sh":65},"17049":{"sx":1085,"sy":733,"sw":82,"sh":33},"17050":{"sx":1231,"sy":744,"sw":56,"sh":33},"17051":{"sx":849,"sy":726,"sw":82,"sh":42},"17054":{"sx":528,"sy":703,"sw":78,"sh":56},"17055":{"sx":1197,"sy":671,"sw":82,"sh":71},"17057":{"sx":933,"sy":726,"sw":75,"sh":45},"17059":{"sx":635,"sy":758,"sw":26,"sh":15},"17060":{"sx":1260,"sy":244,"sw":50,"sh":32},"17062":{"sx":1165,"sy":427,"sw":29,"sh":19}}}}