{"id":136728,"topNeighbourId":136727,"bottomNeighbourId":136729,"leftNeighbourId":137240,"rightNeighbourId":136216,"shadowBonusOnEntities":-1,"cells":[{},{},{"l":3,"c":-32},{"l":67,"c":-32},{"l":67,"c":-32},{"l":3,"c":-32},{"l":67,"c":32},{"l":67,"c":-128},{"l":67,"c":-32},{"l":67,"c":-32},{"l":67,"c":-32},{},{"l":67,"c":-32},{"l":67,"c":-32},{},{},{"l":3,"c":64},{"l":67,"c":64},{"l":67,"c":64},{"l":3,"c":64},{"l":67},{"l":67,"c":64},{"l":67,"c":64},{"l":67,"c":64},{"l":67},{"l":3},{"l":67,"c":64},{"l":67,"c":-61},{},{"l":64},{},{"l":67},{"l":67},{"l":3},{"l":67},{"l":67},{"l":67},{"l":67},{"l":67},{"l":67},{"l":67},{"l":67,"c":1},{"l":67},{},{},{"l":67},{"l":3},{"l":3},{"l":67},{"l":67},{"l":67},{"l":67},{"l":67},{"l":67},{"l":67},{"l":67,"c":-125},{"l":67,"c":8},{"l":67},{},{"l":67},{"l":67},{},{"l":3},{"l":67},{"l":67},{"l":67},{"l":67},{"l":67},{"l":67},{"l":67,"c":1},{"l":67,"c":16},{"l":67},{"l":3},{"l":67},{"l":3},{"l":3},{"l":67},{"l":67},{"l":67},{"l":67},{"l":67},{"l":67},{"l":67},{"l":67,"c":-125},{"l":67,"c":56},{"l":67},{"l":67},{"l":67},{"l":67},{"l":3},{"l":3},{"l":67},{"l":67},{"l":67},{"l":67},{"l":67},{"l":67},{"l":67,"c":1},{"l":67,"c":16},{"l":67},{"l":67},{"l":67},{"l":67},{},{"l":67},{"l":67},{"l":67},{"l":67},{"l":67},{"l":67},{"l":67},{"l":67,"c":-125},{"l":67,"c":56},{"l":67},{"l":67},{"l":67},{"l":67},{},{"l":67},{"l":67},{"l":67},{"l":67},{"l":67},{"l":67},{"l":67},{"l":67,"c":1},{"l":67,"c":16},{"l":67},{"l":67},{"l":67},{"l":67},{"l":67},{"l":67},{"l":67},{"l":67},{"l":67},{"l":67},{"l":67},{"l":67},{"l":67,"c":-125},{"l":67,"c":56},{"l":67},{"l":67},{"l":67},{"l":67},{"l":67},{"l":67},{"l":67},{"l":67},{"l":67},{"l":67},{"l":67},{"l":67},{"l":67,"c":1},{"l":67,"c":16},{"l":67},{"l":67},{"l":67},{"l":67},{"l":67},{"l":67},{"l":67},{"l":67},{"l":67},{"l":67},{"l":67},{"l":67},{"l":67,"c":-125},{"l":67,"c":56},{"l":67},{"l":67},{"l":67},{"l":67},{"l":67},{"l":67},{"l":67},{"l":67},{"l":67},{"l":67},{"l":67},{"l":67},{"l":67,"c":1},{"l":67,"c":16},{"l":67},{"l":67},{"l":67},{"l":67},{"l":67},{"l":67},{"l":67},{"l":67},{"l":67},{"l":67},{"l":67},{"l":67},{"l":67,"c":-125},{"l":67,"c":56},{"l":67},{"l":67},{"l":67},{"l":67},{"l":67},{"l":67},{"l":67},{"l":3},{"l":67},{"l":67},{"l":67},{"l":67},{"l":67,"c":1},{"l":67,"c":16},{"l":67},{"l":67},{"l":67},{"l":67},{"l":67},{"l":67},{"l":67},{"l":67},{"l":67},{"l":67},{"l":67},{"l":67},{"l":67,"c":-125},{"l":67,"c":56},{"l":67},{"l":67},{"l":67},{"l":67},{"l":67},{"l":67},{"l":67},{"l":3},{"l":67},{"l":67},{"l":67},{"l":67},{"l":67,"c":1},{"l":67,"c":16},{"l":67},{"l":67},{"l":67},{"l":67},{"l":67},{"l":67},{"l":67},{"l":67},{"l":67},{"l":67},{"l":67},{"l":67},{"l":67,"c":-125},{"l":67,"c":56},{"l":67},{"l":67},{"l":67},{"l":67},{"l":67},{"l":67},{"l":67},{"l":3},{"l":67},{"l":67},{"l":67},{"l":67},{"l":67,"c":1},{"l":67,"c":16},{"l":67},{"l":67},{"l":67},{"l":67},{"l":67},{"l":67},{"l":3},{"l":3},{"l":67},{"l":67},{"l":67},{"l":67},{"l":67,"c":-125},{"l":67,"c":56},{"l":67},{"l":67},{"l":67},{"l":67},{"l":67},{"l":67},{"l":3},{"l":3},{"l":67},{"l":67},{"l":67},{"l":67},{"l":67,"c":1},{"l":67,"c":16},{"l":67},{"l":67},{"l":67},{"l":67},{"l":67},{"l":67},{},{"l":3},{"l":67},{"l":67},{"l":67},{"l":67},{"l":67,"c":-125},{"l":3,"c":56},{"l":3},{"l":67},{"l":67},{"l":67},{"l":67},{"l":67},{"l":64},{},{"l":3},{"l":67},{"l":67},{"l":67},{"l":67,"c":1},{"l":3,"c":16},{"l":67},{"l":67},{"l":67},{"l":67},{"l":67},{"l":67},{"l":67},{},{"l":67},{"l":67},{"l":67},{"l":67},{"l":67,"c":-125},{"l":3,"c":56},{"l":3},{"l":67},{"l":67},{"l":67},{"l":67},{"l":67},{"l":67},{"l":2},{},{"l":67},{"l":67},{"l":67},{"l":67,"c":1},{"l":3,"c":16},{"l":3},{"l":67},{"l":67},{"l":67},{"l":67},{"l":67},{"l":67},{"l":67},{"l":2},{"l":67},{"l":67},{"l":67},{"l":67,"c":-125},{"l":3,"c":56},{"l":3},{"l":67},{"l":67},{"l":67},{"l":67},{"l":67},{"l":67},{"l":67},{"l":67},{"l":67},{"l":67},{"l":67},{"l":67,"c":1},{"l":3,"c":16},{"l":3},{"l":67},{"l":67},{"l":67},{"l":67},{"l":67},{"l":67},{"l":67},{"l":67},{"l":67},{"l":67},{"l":67},{"l":67,"c":-125},{"l":3,"c":56},{"l":3},{"l":67},{"l":67},{"l":67},{"l":67},{"l":67},{"l":67},{"l":67},{"l":67},{"l":67},{"l":67},{"l":67},{"l":67,"c":1},{"l":3},{"l":2},{"l":67},{"l":67},{"l":67},{"l":67},{"l":67},{"l":67},{"l":67},{"l":67},{"l":67},{"l":67},{"l":67},{"l":67,"c":-125},{},{},{"l":67},{"l":67},{"l":67},{"l":67},{"l":67},{"l":67},{"l":67},{"l":67},{"l":67},{"l":67},{"l":67},{"l":67,"c":1},{},{"l":3},{"l":67},{"l":67},{"l":67},{"l":67},{"l":67},{"l":67},{"l":67},{"l":67},{"l":67},{"l":67},{"l":67},{"l":67,"c":-125},{},{},{"l":67},{"l":67},{"l":67},{"l":67},{"l":67},{"l":67},{"l":67},{"l":67},{"l":67},{"l":67},{"l":67},{"l":67,"c":1},{"l":3},{"l":67},{"l":67},{"l":67},{"l":67},{"l":67},{"l":67},{"l":67},{"l":67},{"l":67},{"l":67},{"l":67},{"l":67},{"l":67,"c":-125},{"l":67,"c":56},{},{"l":67},{"l":67},{"l":67},{"l":67},{"l":67},{"l":67},{"l":67},{"l":67},{"l":67},{"l":67},{"l":67},{"l":67,"c":1},{"l":67,"c":16},{"l":67},{"l":67},{"l":67},{"l":67},{"l":67},{"l":67},{"l":67},{"l":67},{"l":67},{"l":67},{"l":67},{"l":67},{"l":67,"c":-125},{"l":67,"c":56},{"l":67},{"l":67},{"l":67},{"l":67},{"l":67},{"l":67},{"l":67},{"l":67},{"l":67},{"l":67},{"l":67},{"l":67},{"l":67,"c":1},{"l":67,"c":16},{"l":67},{"l":67},{"l":67},{"l":67},{"l":67},{"l":67},{"l":67},{"l":67},{"l":67},{"l":67},{"l":67},{"l":67},{"l":67,"c":-125},{"l":67,"c":60},{"l":67,"c":4},{"l":67,"c":4},{"l":67,"c":4},{"l":67,"c":4},{"l":67,"c":4},{"l":67,"c":4},{"l":67,"c":4},{"l":67,"c":4},{"l":67,"c":4},{"l":3,"c":4},{"l":67,"c":4},{"l":67,"c":4},{"l":67,"c":5},{"l":67,"c":14},{"l":67,"c":14},{"l":67,"c":14},{"l":67,"c":14},{"l":67,"c":10},{"l":67,"c":14},{"l":67,"c":14},{"l":67,"c":14},{"l":67,"c":14},{"l":3,"c":14},{"l":3,"c":14},{"l":3,"c":14},{"l":67,"c":14},{"l":67,"c":-115}],"midgroundLayer":{"11":[{"g":16252,"x":865,"y":-180,"hue":[-27,-27,-27],"cw":181,"ch":212}],"12":[{"g":7715,"x":923,"y":-95,"hue":[0,0,0],"cw":201,"ch":106}],"14":[{"g":11758,"x":12,"y":-23.5,"hue":[-79,-79,-79],"cw":61,"ch":60}],"16":[{"g":16275,"x":252,"y":-48.5,"hue":[-13,-38,-77],"sx":-1,"cw":73,"ch":66}],"22":[{"g":16277,"x":787,"y":-27.5,"hue":[-25,-50,-89],"sx":-1,"cw":105,"ch":67}],"26":[{"g":14426,"x":930,"y":-144.5,"hue":[-77,-78,-98],"cw":403,"ch":266}],"28":[{"g":11815,"x":-47,"y":-136,"hue":[-101,-101,-101],"cy":-121,"cw":118,"ch":76}],"29":[{"g":16251,"x":23,"y":-183,"hue":[-27,-27,-27],"cw":269,"ch":264}],"31":[{"g":16277,"x":314,"y":-6,"hue":[-13,-38,-77],"sx":-1,"cw":105,"ch":67}],"39":[{"g":7715,"x":837,"y":-52,"hue":[0,0,0],"cw":201,"ch":106}],"41":[{"g":16278,"x":1175,"y":-36,"hue":[-25,-50,-89],"sx":-1,"cw":108,"ch":99}],"42":[{"g":12003,"x":-186,"y":-281.5,"hue":[-101,-101,-101],"cx":-133,"cy":-266,"cw":112,"ch":98}],"43":[{"g":16255,"x":75,"y":-28.5,"hue":[-27,-27,-27],"cw":117,"ch":113}],"44":[{"g":16258,"x":168,"y":3.5,"hue":[-27,-27,-27],"cw":107,"ch":79}],"53":[{"g":16275,"x":1026,"y":-5.5,"hue":[-26,-51,-90],"sx":-1,"cw":73,"ch":66}],"56":[{"g":7715,"x":-109,"y":-9,"hue":[-59,-60,-80],"cw":201,"ch":106}],"58":[{"g":16252,"x":91,"y":-94,"hue":[-27,-27,-27],"cw":181,"ch":212}],"59":[{"g":16277,"x":314,"y":37,"hue":[-13,-38,-77],"sx":-1,"cw":105,"ch":67}],"61":[{"g":16252,"x":349,"y":-94,"hue":[-27,-27,-27],"cw":181,"ch":212}],"68":[{"g":16276,"x":1076,"y":46,"hue":[-25,-50,-89],"sx":-1,"cw":87,"ch":53}],"70":[{"g":14426,"x":-102,"y":-58.5,"hue":[-66,-67,-87],"cw":403,"ch":266}],"73":[{"g":16275,"x":338,"y":57.5,"hue":[-13,-38,-77],"sx":-1,"cw":73,"ch":66}],"82":[{"g":16275,"x":1138,"y":56.5,"hue":[-25,-50,-89],"sx":-1,"cw":73,"ch":66}],"97":[{"g":16276,"x":1152,"y":86,"hue":[-23,-48,-87],"sx":-1,"cw":87,"ch":53},{"g":11752,"x":1454,"y":-124,"hue":[-106,-106,-106],"sx":-1,"cw":263,"ch":273}],"98":[{"g":7715,"x":-238,"y":55.5,"hue":[-59,-60,-80],"cw":201,"ch":106}],"101":[{"g":16275,"x":364,"y":99.5,"hue":[-13,-38,-77],"sx":-1,"cw":73,"ch":66}],"103":[{"g":16253,"x":403,"y":-76.5,"hue":[-27,-27,-27],"cw":190,"ch":270}],"110":[{"g":16275,"x":1112,"y":80.5,"hue":[-24,-49,-88],"sx":-1,"cw":73,"ch":66}],"111":[{"g":7715,"x":1138,"y":55.5,"hue":[0,0,0],"cw":201,"ch":106}],"113":[{"g":16275,"x":123,"y":122,"hue":[-14,-39,-78],"sx":-1,"cw":73,"ch":66}],"117":[{"g":11901,"x":343,"y":-15,"hue":[-92,-92,-92],"cw":186,"ch":208}],"125":[{"g":16275,"x":1155,"y":102,"hue":[-23,-48,-87],"sx":-1,"cw":73,"ch":66}],"127":[{"g":16276,"x":163,"y":150.5,"hue":[-14,-39,-78],"sx":-1,"cw":87,"ch":53}],"131":[{"g":7715,"x":364,"y":98.5,"hue":[0,0,0],"cw":201,"ch":106}],"138":[{"g":16275,"x":1112,"y":123.5,"hue":[-23,-48,-87],"sx":-1,"cw":73,"ch":66}],"139":[{"g":14426,"x":1188,"y":27.5,"hue":[-77,-78,-98],"cw":403,"ch":266}],"141":[{"g":16276,"x":120,"y":172,"hue":[-15,-40,-79],"sx":-1,"cw":87,"ch":53}],"167":[{"g":16275,"x":1198,"y":186.5,"hue":[-13,-38,-77],"sx":-1,"cw":73,"ch":66}],"176":[{"g":16278,"x":745,"y":179,"hue":[-19,-44,-83],"sx":-1,"cw":108,"ch":99}],"195":[{"g":16276,"x":1205,"y":239.5,"hue":[-9,-34,-73],"sx":-1,"cw":87,"ch":53}],"196":[{"g":16276,"x":44,"y":261,"hue":[-16,-41,-80],"sx":-1,"cw":87,"ch":53}],"209":[{"g":16275,"x":1155,"y":251,"hue":[-8,-33,-72],"sx":-1,"cw":73,"ch":66}],"210":[{"g":16275,"x":106,"y":271.5,"hue":[-15,-40,-79],"sx":-1,"cw":73,"ch":66}],"224":[{"g":16275,"x":37,"y":274,"hue":[-14,-39,-78],"sx":-1,"cw":73,"ch":66}],"261":[{"g":16277,"x":830,"y":338,"hue":[0,-25,-64],"sx":-1,"cw":105,"ch":67}],"275":[{"g":16276,"x":861,"y":368.5,"hue":[-1,-26,-65],"sx":-1,"cw":87,"ch":53}],"301":[{"g":11756,"x":681,"y":392.5,"hue":[9,9,9],"sx":-1,"cw":82,"ch":79}],"306":[{"g":14426,"x":930,"y":285.5,"hue":[-59,-60,-80],"cw":403,"ch":266}],"314":[{"g":16277,"x":572,"y":424,"hue":[6,-19,-58],"sx":-1,"cw":105,"ch":67}],"315":[{"g":13849,"x":463,"y":380,"hue":[20,20,20],"cw":285,"ch":192}],"316":[{"g":16253,"x":618,"y":246,"hue":[10,10,10],"cw":190,"ch":270}],"324":[{"g":14426,"x":70,"y":328.5,"hue":[-60,-61,-81],"cw":403,"ch":266}],"328":[{"g":16275,"x":596,"y":424.5,"hue":[9,-16,-55],"sx":-1,"cw":73,"ch":66}],"330":[{"g":16256,"x":669,"y":395.5,"hue":[5,5,5],"cw":133,"ch":127}],"344":[{"g":16258,"x":641,"y":455,"hue":[10,10,10],"cw":107,"ch":79}],"345":[{"g":13851,"x":733,"y":474,"hue":[-24,-24,-24],"cw":89,"ch":65}],"350":[{"g":7715,"x":-238,"y":442.5,"hue":[6,6,6],"cw":201,"ch":106}],"351":[{"g":16275,"x":166,"y":487.5,"hue":[-19,-44,-83],"sx":-1,"cw":73,"ch":66}],"358":[{"g":7715,"x":622,"y":442.5,"hue":[0,0,0],"cw":201,"ch":106}],"359":[{"g":11758,"x":786,"y":492.5,"hue":[-32,-32,-32],"cw":61,"ch":60}],"363":[{"g":16278,"x":1304,"y":458.5,"hue":[-8,-33,-72],"sx":-1,"cw":108,"ch":99}],"366":[{"g":14426,"x":27,"y":393,"hue":[-71,-72,-92],"cw":403,"ch":266}],"367":[{"g":16278,"x":315,"y":480,"hue":[-12,-37,-76],"sx":-1,"cw":108,"ch":99}],"368":[{"g":16275,"x":407,"y":508,"hue":[-2,-27,-66],"sx":-1,"cw":73,"ch":66}],"371":[{"g":16276,"x":659,"y":518,"hue":[0,-25,-64],"sx":-1,"cw":87,"ch":53}],"378":[{"g":14426,"x":-446,"y":414.5,"hue":[-45,-46,-66],"cw":403,"ch":266},{"g":7715,"x":-238,"y":485.5,"hue":[6,6,6],"cw":201,"ch":106}],"387":[{"g":16276,"x":861,"y":540.5,"hue":[-3,-28,-67],"sx":-1,"cw":87,"ch":53}],"389":[{"g":16276,"x":1046,"y":539.5,"hue":[-18,-43,-82],"sx":-1,"cw":87,"ch":53}],"394":[{"g":16275,"x":209,"y":552,"hue":[-22,-47,-86],"sx":-1,"cw":73,"ch":66}],"396":[{"g":16275,"x":381,"y":532,"hue":[-2,-27,-66],"sx":-1,"cw":73,"ch":66}],"407":[{"g":16258,"x":82,"y":562.5,"hue":[-27,-27,-27],"cw":107,"ch":79}],"420":[{"g":11754,"x":-52,"y":525,"hue":[-90,-90,-90],"cw":131,"ch":141}],"421":[{"g":16252,"x":5,"y":465,"hue":[-27,-27,-27],"cw":181,"ch":212}],"422":[{"g":16275,"x":235,"y":594,"hue":[-22,-47,-86],"sx":-1,"cw":73,"ch":66}],"434":[{"g":11752,"x":121,"y":413.5,"hue":[-61,-61,-61],"sx":-1,"cw":263,"ch":273}],"442":[{"g":7715,"x":622,"y":571.5,"hue":[0,0,0],"cw":201,"ch":106}],"448":[{"g":7715,"x":-195,"y":593,"hue":[3,3,3],"cw":201,"ch":106},{"g":16251,"x":-63,"y":462,"hue":[-27,-27,-27],"cw":269,"ch":264},{"g":16257,"x":-57,"y":638,"hue":[-27,-27,-27],"cx":-4,"cw":125,"ch":77}],"452":[{"g":16278,"x":401,"y":609,"hue":[-15,-40,-79],"sx":-1,"cw":108,"ch":99}],"469":[{"g":14426,"x":500,"y":543.5,"hue":[-61,-62,-82],"cw":403,"ch":266}],"476":[{"g":14426,"x":-317,"y":565,"hue":[-72,-73,-93],"cw":403,"ch":266},{"g":7715,"x":-109,"y":636,"hue":[-59,-60,-80],"cw":201,"ch":106},{"g":7715,"x":-109,"y":636,"hue":[-59,-60,-80],"cw":201,"ch":106},{"g":14426,"x":-145,"y":565,"hue":[-77,-78,-98],"cw":403,"ch":266}],"477":[{"g":7715,"x":-23,"y":636,"hue":[-70,-70,-70],"cw":201,"ch":106},{"g":11756,"x":51,"y":672,"hue":[-70,-70,-70],"cw":82,"ch":79}],"478":[{"g":16275,"x":209,"y":661,"hue":[-22,-47,-86],"sx":-1,"cw":73,"ch":66}],"489":[{"g":16275,"x":1181,"y":680,"hue":[-25,-50,-89],"sx":-1,"cw":73,"ch":66}],"492":[{"g":16276,"x":249,"y":709.5,"hue":[-22,-47,-86],"sx":-1,"cw":87,"ch":53}],"503":[{"g":16275,"x":1224,"y":701.5,"hue":[-26,-51,-90],"sx":-1,"cw":73,"ch":66}],"506":[{"g":16275,"x":235,"y":723,"hue":[-23,-48,-87],"sx":-1,"cw":73,"ch":66}],"508":[{"g":16276,"x":401,"y":733,"hue":[-19,-44,-83],"sx":-1,"cw":87,"ch":53}],"514":[{"g":16275,"x":923,"y":723,"hue":[-18,-43,-82],"sx":-1,"cw":73,"ch":66}],"517":[{"g":16276,"x":1175,"y":733,"hue":[-25,-50,-89],"sx":-1,"cw":87,"ch":53},{"g":16275,"x":1241,"y":724,"hue":[-19,-44,-83],"sx":-1,"cw":73,"ch":66}],"518":[{"g":16275,"x":-6,"y":745.5,"hue":[-28,-53,-92],"sx":-1,"cw":73,"ch":66}],"524":[{"g":14426,"x":414,"y":629.5,"hue":[-59,-60,-80],"cw":403,"ch":266}],"530":[{"g":16277,"x":1131,"y":746.5,"hue":[-25,-50,-89],"sx":-1,"cw":105,"ch":67}],"536":[{"g":16275,"x":381,"y":747,"hue":[-13,-38,-77],"sx":-1,"cw":73,"ch":66}],"540":[{"g":16277,"x":744,"y":768,"hue":[-11,-36,-75],"sx":-1,"cw":105,"ch":67}],"557":[{"g":16275,"x":1026,"y":788.5,"hue":[-22,-47,-86],"sx":-1,"cw":73,"ch":66}],"560":[{"g":16277,"x":-30,"y":810.5,"hue":[-20,-45,-84],"sx":-1,"cw":105,"ch":67},{"g":16277,"x":56,"y":810.5,"hue":[-11,-36,-75],"sx":-1,"cw":105,"ch":67},{"g":16275,"x":209,"y":809.5,"hue":[-15,-40,-79],"sx":-1,"cw":73,"ch":66},{"g":16276,"x":315,"y":818.5,"hue":[-18,-43,-82],"sx":-1,"cw":87,"ch":53},{"g":16276,"x":722,"y":816.5,"hue":[-26,-51,-90],"sx":-1,"cw":87,"ch":53},{"g":16275,"x":1009,"y":808.5,"hue":[-26,-51,-90],"sx":-1,"cw":73,"ch":66},{"g":14426,"x":-16,"y":715.5,"hue":[-64,-65,-85],"cw":403,"ch":266},{"g":16278,"x":272,"y":802.5,"hue":[-16,-41,-80],"sx":-1,"cw":108,"ch":99},{"g":16258,"x":340,"y":820.5,"hue":[-27,-27,-27],"cw":107,"ch":79},{"g":7715,"x":364,"y":786.5,"hue":[0,0,0],"cw":201,"ch":106},{"g":16275,"x":682,"y":811.5,"hue":[-25,-50,-89],"sx":-1,"cw":73,"ch":66},{"g":16277,"x":1045,"y":832.5,"hue":[-23,-48,-87],"sx":-1,"cw":105,"ch":67},{"g":16255,"x":290,"y":809.5,"hue":[-27,-27,-27],"cw":117,"ch":113},{"g":14426,"x":371,"y":736.5,"hue":[-75,-76,-96],"cw":403,"ch":266},{"g":14426,"x":199,"y":779.5,"hue":[-66,-67,-87],"cw":403,"ch":266},{"g":11755,"x":739,"y":766.5,"hue":[-90,-90,-90],"cw":254,"ch":84},{"g":9542,"x":974,"y":682.5,"hue":[20,20,-53],"cw":240,"ch":168}]},"atlasLayout":{"width":839,"height":636,"graphicsPositions":{"7715":{"sx":720,"sy":194,"sw":30,"sh":16,"cw":201,"ch":106},"9542":{"sx":599,"sy":215,"sw":51,"sh":35,"cw":240,"ch":168},"11752":{"sx":1,"sy":1,"sw":263,"sh":273},"11754":{"sx":668,"sy":215,"sw":131,"sh":141},"11755":{"sx":1,"sy":470,"sw":254,"sh":84},"11756":{"sx":1,"sy":556,"sw":82,"sh":79},"11758":{"sx":704,"sy":566,"sw":61,"sh":60},"11815":{"sx":720,"sy":116,"sw":118,"sh":76,"cy":121},"11901":{"sx":480,"sy":267,"sw":186,"sh":208},"12003":{"sx":480,"sy":477,"sw":112,"sh":98,"cx":133,"cy":266},"13849":{"sx":1,"sy":276,"sw":285,"sh":192},"13851":{"sx":85,"sy":556,"sw":89,"sh":65},"14426":{"sx":537,"sy":215,"sw":60,"sh":40,"cw":403,"ch":266},"16251":{"sx":266,"sy":1,"sw":269,"sh":264},"16252":{"sx":537,"sy":1,"sw":181,"sh":212},"16253":{"sx":288,"sy":267,"sw":190,"sh":270},"16255":{"sx":720,"sy":1,"sw":117,"sh":113},"16256":{"sx":668,"sy":358,"sw":133,"sh":127},"16257":{"sx":704,"sy":487,"sw":125,"sh":77,"cx":4},"16258":{"sx":257,"sy":539,"sw":107,"sh":79},"16275":{"sx":176,"sy":556,"sw":73,"sh":66},"16276":{"sx":473,"sy":577,"sw":87,"sh":53},"16277":{"sx":366,"sy":539,"sw":105,"sh":67},"16278":{"sx":594,"sy":487,"sw":108,"sh":99}}}}