{"id":84678661,"topNeighbourId":84678660,"bottomNeighbourId":84678662,"leftNeighbourId":84678149,"rightNeighbourId":84679173,"shadowBonusOnEntities":-1,"cells":[{"l":3,"c":-40},{"l":67,"c":-32},{"l":67,"c":-32},{"l":67,"c":-32},{"l":67,"c":-32},{"l":67,"c":-32},{"l":67,"c":-32},{"l":67,"c":-32},{"l":67,"c":-32},{"l":67,"c":-32},{"l":67,"c":-32},{"l":67,"c":-32},{"l":67,"c":-32},{"l":67,"c":32},{"l":67,"c":80},{"l":67,"c":64},{"l":67,"c":64},{"l":67,"c":64},{"l":67,"c":64},{"l":67,"c":64},{"l":67,"c":64},{"l":67,"c":64},{"l":67,"c":64},{"l":67,"c":64},{"l":67,"c":64},{"l":67,"c":64},{"l":67,"c":64},{"l":67},{"l":3,"c":56},{"l":67},{"l":3},{"l":67},{"l":67},{"l":67},{"l":67},{"l":67},{"l":67},{"l":67},{"l":67},{"l":67},{"l":67},{"l":67},{},{"l":3},{"l":67},{"l":2},{"l":67},{"l":67},{"l":67},{"l":67},{"l":67},{"l":67},{"l":67},{"l":67},{"l":67},{"l":67},{},{"l":67},{},{"l":67},{"l":67},{"l":67},{"l":67},{"l":67},{"l":67},{"l":67},{"l":67},{"l":67},{"l":67},{"l":67},{"l":3},{"l":2},{"l":2},{"l":67},{"l":67},{"l":67},{"l":67},{"l":67},{"l":67},{"l":67},{"l":67},{"l":67},{"l":67},{"l":66},{"l":67,"c":40},{"l":2},{"l":67},{"l":67},{"l":67},{"l":67},{"l":67},{"l":67},{"l":67},{"l":67},{"l":67},{"l":67},{"l":67},{"l":66},{"l":66},{"l":67},{"l":67},{"l":67},{"l":67},{"l":3},{"l":67},{"l":67},{"l":67},{"l":67},{"l":67},{"l":67},{"l":66},{"l":66},{"l":2},{"l":67},{"l":67},{"l":67},{"l":67},{"l":67},{"l":3},{"l":67},{"l":67},{"l":67},{"l":67},{"l":67},{"l":67},{"l":66},{"l":67},{"l":67},{"l":67},{"l":67},{"l":67},{"l":3},{"l":3},{"l":67},{"l":67},{"l":67},{"l":67},{"l":66},{"l":66},{"l":66},{"l":67,"c":8},{"l":67},{"l":67},{"l":67},{"l":67},{"l":3},{"l":3},{"l":67},{"l":67},{"l":67},{"l":67},{"l":66},{"l":66},{"l":66},{"l":67,"c":16},{"l":67},{"l":67},{"l":67},{"l":67},{"l":3},{"l":3},{"l":67},{"l":67},{"l":67},{"l":66},{"l":66},{"l":66},{"l":66},{"l":67,"c":56},{"l":67},{"l":67},{"l":67},{"l":67},{"l":67},{"l":3},{"l":3},{"l":67},{"l":67},{"l":66},{"l":66},{"l":66},{"l":66},{"l":67,"c":16},{"l":67},{"l":67},{"l":67},{"l":67},{"l":67},{"l":3},{"l":67},{"l":67},{"l":66},{"l":66},{"l":66},{"l":66},{"l":66},{"l":67,"c":56},{"l":67},{"l":67},{"l":67},{"l":67},{"l":67},{"l":3},{"l":3},{"l":67},{"l":67},{"l":66},{"l":66},{"l":66},{"l":66},{"l":67,"c":16},{"l":67},{"l":67},{"l":67},{"l":67},{"l":67},{"l":3},{"l":67},{"l":67},{"l":67},{"l":66},{"l":66},{"l":66},{"l":66},{"l":67,"c":56},{"l":67},{"l":67},{"l":67},{"l":67},{"l":67},{"l":3},{"l":67},{"l":67},{"l":67},{"l":67},{"l":66},{"l":66},{"l":66},{"l":3,"c":16},{"l":67},{"l":67},{"l":67},{"l":67},{"l":67},{"l":3},{"l":67},{"l":67},{"l":67},{"l":67},{"l":66},{"l":66},{"l":66},{"l":67,"c":56},{"l":67},{"l":67},{"l":67},{"l":67},{"l":67},{"l":3},{"l":67},{"l":67},{"l":67},{"l":67},{"l":66},{"l":66},{"l":66},{"l":3,"c":16},{"l":67},{"l":67},{"l":67},{"l":67},{"l":67},{"l":3},{"l":67},{"l":67},{"l":67},{"l":67},{"l":66},{"l":66},{"l":66},{"l":3,"c":56},{"l":3},{"l":67},{"l":67},{"l":67},{"l":3},{},{"l":67},{"l":67},{"l":67},{"l":67},{"l":66},{"l":66},{"l":66},{"l":3,"c":16},{"l":67},{"l":67},{"l":67},{"l":67},{"l":67},{},{"l":67},{"l":67},{"l":67},{"l":67},{"l":66},{"l":66},{"l":66},{"l":3,"c":56},{"l":3},{"l":67},{"l":67},{"l":67},{"l":67},{"l":67},{"l":67},{"l":67},{"l":67},{"l":67},{"l":67},{"l":66},{"l":66},{"l":3,"c":16},{"l":67},{"l":3},{"l":67},{"l":67},{"l":67},{"l":67},{"l":67},{"l":67},{"l":67},{"l":67},{"l":66},{"l":66},{"l":66},{"l":3,"c":56},{"l":3},{"l":2},{"l":3},{"l":67},{"l":67},{"l":67},{"l":67},{"l":67},{"l":67},{"l":67},{"l":66},{"l":66},{"l":66},{"l":3},{"l":2},{"l":2},{"l":3},{"l":67},{"l":67},{"l":67},{"l":67},{"l":67},{"l":67},{"l":66},{"l":66},{"l":66},{"l":66},{},{},{"l":67},{"l":3},{"l":67},{"l":67},{"l":67},{"l":67},{"l":67},{"l":67},{"l":67},{"l":66},{"l":66},{"l":66},{},{"l":67},{"l":67},{"l":67},{"l":67},{"l":67},{"l":67},{"l":67},{"l":67},{"l":67},{"l":67},{"l":66},{"l":66},{"l":66},{"l":3,"c":56},{"l":67},{"l":67},{"l":67},{"l":67},{"l":67},{"l":67},{"l":67},{"l":67},{"l":67},{"l":67},{"l":67},{"l":66},{"l":66},{"l":67,"c":16},{"l":67},{"l":67},{"l":67},{"l":67},{"l":67},{"l":67},{"l":67},{"l":67},{"l":67},{"l":67},{"l":67},{"l":66},{"l":66},{"l":67,"c":56},{"l":67},{"l":67},{"l":67},{"l":67},{"l":67},{"l":67},{"l":67},{"l":67},{"l":67},{"l":67},{"l":67},{"l":66},{"l":66},{"l":67,"c":16},{"l":67},{"l":67},{"l":67},{"l":67},{"l":67},{"l":67},{"l":67},{"l":67},{"l":67},{"l":67},{"l":67},{"l":66},{"l":66},{"l":67,"c":32},{"l":3},{"l":67},{"l":67},{"l":67},{"l":67},{"l":67},{"l":67},{"l":67},{"l":67},{"l":67},{"l":67},{"l":67},{"l":66},{"l":3},{"l":67},{"l":67},{"l":67},{"l":67},{"l":67},{"l":67},{"l":67},{"l":67},{"l":67},{"l":67},{"l":67},{"l":67},{"l":66},{"l":3,"c":8},{"l":3},{"l":67},{"l":67},{"l":67},{"l":67},{"l":67},{"l":67},{"l":67},{"l":67},{"l":67},{"l":3},{"l":67},{"l":67},{"l":67,"c":16},{"l":67},{"l":67},{"l":67},{"l":67},{"l":67},{"l":67},{"l":67},{"l":67},{"l":3},{"l":3},{"l":67},{"l":67},{"l":67},{"l":3,"c":56},{"l":3},{"l":67},{"l":67},{"l":67},{"l":67},{"l":67},{"l":67},{"l":67},{"l":67},{"l":3},{"l":3},{"l":67},{"l":67},{"l":3,"c":16},{"l":3},{"l":67},{"l":67},{"l":67},{"l":67},{"l":67},{"l":67},{"l":67},{"l":67},{"l":3},{"l":67},{"l":3},{"l":67},{"l":3,"c":60},{"l":3,"c":4},{"l":67,"c":4},{"l":67,"c":4},{"l":67,"c":4},{"l":67,"c":4},{"l":67,"c":4},{"l":67,"c":4},{"l":67,"c":4},{"l":67,"c":4},{"l":3,"c":4},{"l":3,"c":4},{"l":3,"c":4},{"l":67,"c":4},{"l":3,"c":14},{"l":67,"c":14},{"l":67,"c":14},{"l":67,"c":14},{"l":67,"c":14},{"l":67,"c":14},{"l":67,"c":14},{"l":67,"c":14},{"l":67,"c":14},{"l":67,"c":14},{"l":67,"c":14},{"l":67,"c":14},{"l":3,"c":14},{"l":67,"c":12}],"midgroundLayer":{"0":[{"g":9487,"x":-41,"y":-20,"hue":[0,0,0],"cy":-5,"cw":183,"ch":138}],"42":[{"g":19977,"x":-1,"y":-146.5,"hue":[0,0,0],"cw":106,"ch":231}],"45":[{"g":7398,"x":259,"y":36.5,"hue":[0,0,0],"cw":88,"ch":51}],"56":[{"g":17049,"x":-122,"y":68,"hue":[5,4,-1],"cx":-69,"cw":13,"ch":33},{"g":14353,"x":-87,"y":-113,"hue":[1,1,0],"cx":-34,"cw":113,"ch":222}],"58":[{"g":7401,"x":132,"y":16,"hue":[0,0,0],"cw":86,"ch":94}],"59":[{"g":11496,"x":217,"y":1,"hue":[0,0,0],"cw":80,"ch":106}],"70":[{"g":39,"x":-81,"y":76.5,"hue":[3,3,0],"cx":-28,"cw":46,"ch":44},{"g":700877,"x":74,"y":77.5,"hue":[30,30,30],"sx":-1,"cw":82,"ch":46}],"71":[{"g":7399,"x":89,"y":54.5,"hue":[0,0,0],"cw":93,"ch":70}],"72":[{"g":7400,"x":182,"y":68.5,"hue":[0,0,0],"cw":71,"ch":57}],"84":[{"g":32460,"x":-116,"y":101,"hue":[3,2,-1],"cx":-63,"cw":13,"ch":49},{"g":700398,"x":36,"y":98,"hue":[1,1,0],"sx":-1,"cw":80,"ch":50}],"85":[{"g":17051,"x":31,"y":107,"hue":[0,0,0],"cw":82,"ch":42},{"g":17554,"x":56,"y":79,"hue":[0,0,0],"cw":78,"ch":70},{"g":30161,"x":-23,"y":34,"hue":[0,0,0],"cw":197,"ch":103}],"86":[{"g":30161,"x":63,"y":34,"hue":[0,0,0],"cw":197,"ch":103}],"98":[{"g":700877,"x":-12,"y":120.5,"hue":[32,32,30],"sx":-1,"cw":82,"ch":46},{"g":17556,"x":16,"y":112.5,"hue":[0,0,0],"cw":63,"ch":60},{"g":30161,"x":-66,"y":55.5,"hue":[0,0,0],"cw":197,"ch":103}],"100":[{"g":36331,"x":196,"y":133.5,"hue":[0,0,0],"cw":33,"ch":34}],"112":[{"g":30161,"x":-195,"y":77,"hue":[3,2,-1],"cw":197,"ch":103},{"g":17561,"x":-32,"y":137,"hue":[1,1,0],"cw":61,"ch":55}],"126":[{"g":17556,"x":-70,"y":155.5,"hue":[2,2,0],"cw":63,"ch":60}],"165":[{"look":1018,"x":989,"y":236.5,"hue":[-59,21,56],"id":479488}],"168":[],"193":[{"look":1019,"x":989,"y":279.5,"hue":[-59,21,56],"id":479489}],"207":[{"look":1018,"x":946,"y":301,"hue":[-59,21,56],"id":479490}],"239":[{"g":16105,"x":165,"y":310.5,"hue":[3,2,-1],"sx":-1,"cw":25,"ch":58}],"286":[{"g":38728,"x":391,"y":129,"hue":[0,0,0],"cw":223,"ch":326}],"300":[{"g":38727,"x":639,"y":232.5,"hue":[0,0,0],"sx":-1,"cw":121,"ch":235}],"313":[{"g":12040,"x":394,"y":373,"hue":[0,0,0],"cw":80,"ch":105}],"315":[{"g":17905,"x":570,"y":447,"hue":[0,0,0],"cw":99,"ch":43}],"351":[{"g":12221,"x":126,"y":481.5,"hue":[3,2,-1],"cw":153,"ch":93},{"g":7397,"x":86,"y":516.5,"hue":[3,2,-1],"cw":86,"ch":44}],"361":[{"look":1018,"x":989,"y":537.5,"hue":[-59,21,56],"id":479491}],"364":[{"g":14369,"x":-84,"y":326,"hue":[7,5,-1],"cx":-31,"cw":155,"ch":254}],"365":[{"g":7408,"x":35,"y":492,"hue":[4,3,-1],"cw":115,"ch":91}],"366":[{"g":700877,"x":203,"y":529,"hue":[32,32,30],"sx":-1,"cw":82,"ch":46},{"g":700771,"x":114,"y":518,"hue":[2,2,0],"cw":107,"ch":57}],"367":[{"g":11497,"x":202,"y":450,"hue":[0,0,0],"cw":109,"ch":139}],"378":[{"g":700877,"x":74,"y":550.5,"hue":[35,34,29],"sx":-1,"cw":82,"ch":46},{"g":14354,"x":-7,"y":401.5,"hue":[5,4,-1],"cw":115,"ch":197}],"381":[{"g":11491,"x":265,"y":478.5,"hue":[0,0,0],"cw":81,"ch":105}],"390":[{"look":1019,"x":1075,"y":580.5,"hue":[-59,21,56],"id":479492}],"392":[{"g":12040,"x":-122,"y":502,"hue":[11,8,-3],"cw":80,"ch":105},{"g":700877,"x":-33,"y":572,"hue":[37,35,29],"cw":82,"ch":46}],"394":[{"g":30161,"x":63,"y":507,"hue":[2,2,0],"cw":197,"ch":103}],"406":[{"g":30161,"x":-66,"y":528.5,"hue":[5,4,-1],"cw":197,"ch":103}],"434":[{"g":30161,"x":-238,"y":571.5,"hue":[10,8,-2],"cw":197,"ch":103}],"455":[{"g":16104,"x":634,"y":615,"hue":[0,0,0],"sx":-1,"cw":52,"ch":73}],"456":[{"g":16103,"x":644,"y":569,"hue":[0,0,0],"cw":51,"ch":120}],"462":[{"g":14355,"x":-112,"y":482.5,"hue":[7,5,-2],"cx":-59,"cw":84,"ch":247}],"476":[{"g":700877,"x":-119,"y":701,"hue":[38,36,28],"cw":82,"ch":46},{"g":17049,"x":-122,"y":713,"hue":[8,6,-2],"cx":-69,"cw":13,"ch":33},{"g":700877,"x":31,"y":701,"hue":[36,34,29],"sx":-1,"cw":82,"ch":46}],"477":[{"g":11493,"x":49,"y":615,"hue":[4,3,-1],"cw":80,"ch":119}],"478":[{"g":17051,"x":117,"y":709,"hue":[2,2,0],"cw":82,"ch":42}],"490":[{"g":30161,"x":-238,"y":657.5,"hue":[8,6,-2],"cw":197,"ch":103}],"504":[{"g":30161,"x":-109,"y":679,"hue":[7,5,-1],"cw":197,"ch":103}],"507":[{"g":700398,"x":294,"y":743,"hue":[1,1,0],"sx":-1,"cw":80,"ch":50}],"520":[{"g":18,"x":198,"y":778.5,"hue":[3,3,0],"cw":34,"ch":33}],"521":[{"g":700399,"x":257,"y":761.5,"hue":[2,2,0],"cw":90,"ch":50}],"560":[{"g":14352,"x":-56,"y":661.5,"hue":[11,8,-3],"cx":-3,"cw":186,"ch":189},{"g":19977,"x":42,"y":734.5,"hue":[9,7,-2],"cw":106,"ch":231},{"g":14353,"x":-87,"y":789.5,"hue":[8,6,-2],"cx":-34,"cw":113,"ch":222},{"g":38726,"x":799,"y":691.5,"hue":[0,0,0],"cw":179,"ch":159},{"g":38728,"x":1157,"y":773.5,"hue":[3,2,-1],"sx":-1,"cw":223,"ch":326}]},"atlasLayout":{"width":1019,"height":512,"graphicsPositions":{"18":{"sx":182,"sy":365,"sw":34,"sh":33},"39":{"sx":936,"sy":365,"sw":46,"sh":44,"cx":28},"7397":{"sx":910,"sy":419,"sw":86,"sh":44},"7398":{"sx":274,"sy":448,"sw":88,"sh":51},"7399":{"sx":849,"sy":1,"sw":93,"sh":70},"7400":{"sx":896,"sy":73,"sw":71,"sh":57},"7401":{"sx":840,"sy":201,"sw":86,"sh":94},"7408":{"sx":732,"sy":1,"sw":115,"sh":91},"9487":{"sx":840,"sy":297,"sw":27,"sh":21,"cy":5,"cw":183,"ch":138},"11491":{"sx":757,"sy":215,"sw":81,"sh":105},"11493":{"sx":732,"sy":94,"sw":80,"sh":119},"11496":{"sx":801,"sy":322,"sw":80,"sh":106},"11497":{"sx":646,"sy":250,"sw":109,"sh":139},"12040":{"sx":814,"sy":94,"sw":80,"sh":105},"12221":{"sx":646,"sy":391,"sw":153,"sh":93},"14352":{"sx":226,"sy":257,"sw":186,"sh":189,"cx":3},"14353":{"sx":414,"sy":238,"sw":113,"sh":222,"cx":34},"14354":{"sx":529,"sy":234,"sw":115,"sh":197},"14355":{"sx":646,"sy":1,"sw":84,"sh":247,"cx":59},"14369":{"sx":226,"sy":1,"sw":155,"sh":254,"cx":31},"16103":{"sx":883,"sy":297,"sw":51,"sh":120},"16104":{"sx":928,"sy":184,"sw":52,"sh":73},"16105":{"sx":757,"sy":322,"sw":25,"sh":58},"17049":{"sx":883,"sy":419,"sw":4,"sh":9,"cx":69,"cw":13,"ch":33},"17051":{"sx":936,"sy":321,"sw":82,"sh":42},"17554":{"sx":529,"sy":433,"sw":78,"sh":70},"17556":{"sx":936,"sy":259,"sw":63,"sh":60},"17561":{"sx":944,"sy":1,"sw":61,"sh":55},"17905":{"sx":364,"sy":462,"sw":99,"sh":43},"19977":{"sx":506,"sy":1,"sw":106,"sh":231},"30161":{"sx":896,"sy":184,"sw":30,"sh":15,"cw":197,"ch":103},"32460":{"sx":889,"sy":419,"sw":2,"sh":7,"cx":63,"cw":13,"ch":49},"36331":{"sx":182,"sy":329,"sw":33,"sh":34},"38726":{"sx":1,"sy":329,"sw":179,"sh":159},"38727":{"sx":383,"sy":1,"sw":121,"sh":235},"38728":{"sx":1,"sy":1,"sw":223,"sh":326},"700398":{"sx":896,"sy":132,"sw":80,"sh":50},"700399":{"sx":182,"sy":448,"sw":90,"sh":50},"700771":{"sx":801,"sy":430,"sw":107,"sh":57},"700877":{"sx":910,"sy":465,"sw":82,"sh":46}}}}