{"id":85721602,"topNeighbourId":85721601,"bottomNeighbourId":85721603,"leftNeighbourId":85721090,"rightNeighbourId":85722114,"shadowBonusOnEntities":-1,"cells":[{"l":2},{"l":2},{"l":2},{"l":2},{"l":2},{"l":2},{"l":67,"c":-32},{"l":67,"c":-32},{"l":67,"c":-32},{"l":67,"c":32},{"l":2},{"l":2},{"l":2},{"l":2},{"l":2},{"l":2},{"l":2},{"l":2},{"l":2},{"l":2},{"l":67,"c":64},{"l":67,"c":64},{"l":67,"c":64},{"l":2},{"l":2},{"l":2},{"l":2},{"l":2},{"l":2},{"l":2},{"l":2},{"l":2},{"l":2},{"l":2},{"l":66},{"l":66},{"l":66},{"l":2},{"l":2},{"l":2},{"l":2},{"l":2},{"l":2},{"l":2},{"l":2},{"l":2},{"l":2},{"l":2},{"l":2},{"l":2},{"l":2},{"l":2},{"l":2},{"l":2},{"l":2},{"l":2},{"l":2},{"l":2},{"l":2},{"l":2},{"l":2},{"l":2},{"l":2},{"l":2},{"l":2},{"l":2},{"l":2},{"l":2},{"l":2},{"l":2},{"l":2},{"l":2},{"l":2},{"l":2},{"l":2},{"l":2},{"l":2},{"l":2},{"l":2},{"l":2},{"l":2},{"l":2},{"l":2},{"l":2},{"l":2},{"l":2},{"l":66},{"l":2},{"l":2},{"l":66},{"l":66},{"l":66},{"l":66},{"l":66},{"l":66},{"l":66},{"l":2},{"l":2},{"l":2},{"l":66},{"l":2},{"l":66},{"l":66},{"l":66},{"l":66},{"l":66},{"l":66},{"l":66},{"l":66},{"l":2},{"l":2},{"l":2},{"l":2},{"l":2},{"l":66},{"l":66},{"l":2},{"l":66},{"l":66},{"l":66},{"l":66},{"l":66},{"l":66},{"l":2},{"l":2},{"l":2},{"l":66},{"l":66},{"l":66},{"l":66},{"l":66},{"l":66},{"l":66},{"l":66},{"l":66},{"l":66},{"l":66},{"l":2},{"l":2},{"l":2},{"l":66},{"l":66},{"l":66},{"l":66},{"l":2},{"l":66},{"l":66},{"l":66},{"l":66},{"l":66},{"l":66},{"l":66},{"l":66},{"l":66},{"l":66},{"l":66},{"l":66},{"l":66},{"l":66},{"l":66},{"l":66},{"l":66},{"l":66},{"l":66},{"l":66},{"l":66},{"l":66},{"l":66},{"l":66},{"l":66},{"l":66},{"l":66},{"l":66},{"l":66},{"l":66},{"l":66},{"l":66},{"l":66},{"l":66},{"l":66},{"l":66},{"l":66},{"l":66},{"l":66},{"l":66},{"l":66},{"l":66},{"l":66},{"l":66},{"l":66},{"l":66},{"l":66},{"l":66},{"l":66},{"l":66},{"l":66},{"l":66},{"l":66},{"l":66},{"l":66},{"l":66},{"l":66},{"l":66},{"l":66},{"l":66},{"l":66},{"l":66},{"l":66},{"l":66},{"l":66},{"l":66},{"l":66},{"l":66},{"l":66},{"l":66},{"l":66},{"l":66},{"l":66},{"l":66},{"l":66},{"l":66},{"l":66},{"l":66},{"l":66},{"l":66},{"l":66},{"l":66},{"l":66},{"l":66},{"l":66},{"l":66},{"l":66},{"l":66},{"l":66},{"l":66},{"l":66},{"l":66},{"l":66},{"l":66},{"l":66},{"l":66},{"l":66},{"l":66},{"l":66},{"l":66},{"l":66},{"l":66},{"l":66},{"l":66},{"l":66},{"l":66},{"l":66},{"l":66},{"l":66},{"l":66},{"l":66},{"l":66},{"l":66},{"l":66},{"l":66},{"l":66},{"l":66},{"l":66},{"l":66},{"l":66},{"l":66},{"l":66},{"l":66},{"l":66},{"l":66},{"l":66},{"l":66},{"l":66},{"l":66},{"l":66},{"l":66},{"l":66},{"l":66},{"l":66},{"l":66},{"l":66},{"l":66},{"l":66},{"l":66},{"l":66},{"l":66},{"l":66},{"l":66},{"l":66},{"l":66},{"l":66},{"l":66},{"l":66},{"l":66},{"l":66},{"l":66},{"l":66},{"l":66},{"l":66},{"l":66},{"l":66},{"l":66},{"l":66},{"l":66},{"l":66},{"l":66},{"l":66},{"l":66},{"l":66},{"l":66},{"l":2},{"l":66},{"l":66},{"l":66},{"l":66},{"l":66},{"l":66},{"l":66},{"l":66},{"l":66},{"l":66},{"l":66},{"l":66},{"l":2},{"l":2},{"l":66},{"l":66},{"l":66},{"l":66},{"l":66},{"l":66},{"l":66},{"l":66},{"l":66},{"l":66},{"l":66},{"l":66},{"l":2},{"l":2},{"l":66},{"l":66},{"l":66},{"l":66},{"l":66},{"l":66},{"l":66},{"l":66},{"l":66},{"l":66},{"l":66},{"l":66},{"l":2},{"l":2},{"l":66},{"l":66},{"l":66},{"l":66},{"l":66},{"l":66},{"l":66},{"l":66},{"l":66},{"l":2},{"l":66},{"l":66},{"l":2},{"l":2},{"l":2},{"l":66},{"l":66},{"l":66},{"l":66},{"l":66},{"l":66},{"l":66},{"l":2},{"l":2},{"l":2},{"l":66},{"l":2},{"l":2},{"l":66},{"l":66},{"l":66},{"l":66},{"l":66},{"l":66},{"l":66},{"l":66},{"l":2},{"l":2},{"l":66},{"l":66},{"l":2},{"l":2},{"l":2},{"l":2},{"l":66},{"l":66},{"l":66},{"l":66},{"l":66},{"l":66},{"l":2},{"l":2},{"l":2},{"l":66},{"l":2},{"l":2},{"l":2},{"l":66},{"l":66},{"l":66},{"l":66},{"l":2},{"l":66},{"l":66},{"l":2},{"l":2},{"l":66},{"l":2},{"l":2},{"l":2},{"l":2},{"l":2},{"l":66},{"l":66},{"l":66},{"l":66},{"l":66},{"l":66},{"l":2},{"l":2},{"l":2},{"l":2},{"l":2},{"l":2},{"l":2},{"l":66},{"l":66},{"l":66},{"l":66},{"l":66},{"l":66},{"l":66},{"l":2},{"l":2},{"l":2},{"l":2},{"l":2},{"l":2},{"l":2},{"l":2},{"l":66},{"l":66},{"l":66},{"l":66},{"l":66},{"l":66},{"l":2},{"l":2},{"l":2},{"l":2},{"l":2},{"l":2},{"l":2},{"l":2},{"l":66},{"l":2},{"l":66},{"l":66},{"l":66},{"l":66},{"l":2},{"l":2},{"l":2},{"l":2},{"l":2},{"l":2},{"l":2},{"l":2},{"l":2},{"l":66},{"l":66},{"l":66},{"l":66},{"l":66},{"l":2},{"l":2},{"l":2},{"l":2},{"l":2},{"l":2},{"l":2},{"l":2},{"l":66},{"l":2},{"l":66},{"l":66},{"l":66},{"l":2},{"l":2},{"l":2},{"l":2},{"l":2},{"l":2},{"l":2},{"l":2},{"l":2},{"l":2},{"l":2},{"l":2},{"l":66},{"l":66},{"l":2},{"l":2},{"l":2},{"l":2},{"l":2},{"l":2},{"l":2},{"l":2},{"l":2},{"l":66},{"l":2},{"l":66},{"l":66},{"l":66},{"l":2},{"l":2},{"l":2},{"l":2},{"l":2},{"l":2},{"l":2},{"l":2},{"l":2},{"l":2},{"l":2},{"l":2},{"l":66},{"l":2},{"l":2},{"l":2},{"l":2},{"l":2},{"l":2},{"l":2},{"l":2},{"l":2},{"l":2},{"l":2},{"l":2},{"l":2},{"l":2},{"l":2},{"l":2},{"l":2},{"l":2},{"l":2}],"midgroundLayer":{"9":[{"g":17049,"x":738,"y":-18,"hue":[-44,-61,-102],"cy":-3,"cw":82,"ch":30}],"560":[{"g":701211,"x":191,"y":-125.5,"hue":[-128,-128,-128],"sx":-1,"cy":-110,"cw":240,"ch":135},{"g":17053,"x":375,"y":-39,"hue":[-41,-58,-99],"cy":-24,"cw":135,"ch":63},{"g":31745,"x":-85,"y":-884.5,"hue":[-42,-59,-100],"cx":-32,"cy":-869,"cw":1267,"ch":129},{"g":13768,"x":892,"y":-84.5,"hue":[-128,-128,-128],"cy":-26,"cw":233,"ch":186},{"g":13768,"x":118,"y":-41.5,"hue":[-128,-128,-128],"cy":-26,"cw":233,"ch":186},{"g":17702,"x":-316,"y":-1224,"hue":[-128,-128,-128],"cy":-1187,"cw":466,"ch":248},{"g":13766,"x":446,"y":-163,"hue":[-56,-73,-114],"sx":-1,"cy":-148,"cw":243,"ch":255},{"g":17702,"x":931,"y":-1202.5,"hue":[-128,-128,-128],"cy":-1187,"cw":466,"ch":248},{"g":24142,"x":734,"y":785.5,"hue":[38,15,-31],"cw":69,"ch":65},{"g":24149,"x":428,"y":788.5,"hue":[48,22,-24],"cw":96,"ch":62},{"g":24142,"x":519,"y":807.5,"hue":[47,21,-25],"cw":69,"ch":65},{"g":24142,"x":605,"y":807.5,"hue":[50,24,-21],"cw":69,"ch":65},{"g":24142,"x":691,"y":807.5,"hue":[42,17,-29],"cw":69,"ch":65},{"g":24149,"x":772,"y":788.5,"hue":[31,6,-38],"cw":96,"ch":62},{"g":24170,"x":460,"y":681.5,"hue":[50,24,-22],"cw":183,"ch":169},{"g":701278,"x":648,"y":742.5,"hue":[49,24,-22],"sx":-1,"cw":92,"ch":108},{"g":24148,"x":740,"y":794.5,"hue":[44,19,-25],"sx":-1,"cw":108,"ch":56},{"g":13764,"x":379,"y":307.5,"hue":[30,4,-41],"sx":-1,"cw":431,"ch":543},{"g":34640,"x":339,"y":679.5,"hue":[49,22,-24],"cw":94,"ch":171},{"g":24149,"x":600,"y":831.5,"hue":[50,24,-21],"cw":96,"ch":62},{"g":701281,"x":476,"y":832.5,"hue":[48,22,-24],"sx":-1,"cw":91,"ch":18},{"g":24148,"x":464,"y":837.5,"hue":[55,28,-18],"cw":108,"ch":56},{"g":20067,"x":758,"y":731.5,"hue":[36,13,-33],"cw":240,"ch":119},{"g":13765,"x":-178,"y":543.5,"hue":[21,-4,-48],"cx":-125,"cw":212,"ch":307},{"g":24168,"x":465,"y":835.5,"hue":[51,25,-21],"cw":181,"ch":15},{"g":701224,"x":811,"y":849.5,"hue":[26,3,-41],"cw":94,"ch":1},{"g":13764,"x":1282,"y":371.5,"hue":[17,-6,-50],"sx":-1,"cw":431,"ch":543},{"g":30926,"x":438,"y":838.5,"hue":[49,23,-23],"cw":111,"ch":12},{"g":19232,"x":685,"y":502.5,"hue":[-118,-128,-128],"cw":316,"ch":348},{"g":24035,"x":1094,"y":600.5,"hue":[-128,-128,-128],"cw":120,"ch":250},{"g":19232,"x":83,"y":545.5,"hue":[-121,-128,-128],"cw":316,"ch":348},{"g":17769,"x":900,"y":647.5,"hue":[-128,-128,-128],"cw":314,"ch":203},{"g":19204,"x":232,"y":572.5,"hue":[-128,-128,-128],"sx":-1,"cw":285,"ch":278}]},"atlasLayout":{"width":896,"height":1238,"graphicsPositions":{"13764":{"sx":1,"sy":1,"sw":431,"sh":543},"13765":{"sx":434,"sy":1,"sw":212,"sh":307,"cx":125},"13766":{"sx":648,"sy":1,"sw":243,"sh":255,"cy":148},"13768":{"sx":469,"sy":515,"sw":233,"sh":186,"cy":26},"17049":{"sx":648,"sy":258,"sw":82,"sh":30,"cy":3},"17053":{"sx":469,"sy":703,"sw":135,"sh":63,"cy":24},"17702":{"sx":1,"sy":546,"sw":466,"sh":248,"cy":1187},"17769":{"sx":434,"sy":310,"sw":314,"sh":203},"19204":{"sx":319,"sy":796,"sw":285,"sh":278},"19232":{"sx":1,"sy":796,"sw":316,"sh":348},"20067":{"sx":606,"sy":840,"sw":240,"sh":119},"24035":{"sx":750,"sy":258,"sw":120,"sh":250},"24142":{"sx":527,"sy":1076,"sw":69,"sh":65},"24148":{"sx":319,"sy":1076,"sw":108,"sh":56},"24149":{"sx":429,"sy":1076,"sw":96,"sh":62},"24168":{"sx":434,"sy":515,"sw":27,"sh":2,"cw":181,"ch":15},"24170":{"sx":704,"sy":515,"sw":183,"sh":169},"30926":{"sx":434,"sy":519,"sw":17,"sh":2,"cw":111,"ch":12},"31745":{"sx":1,"sy":1146,"sw":894,"sh":91,"cx":32,"cy":869,"cw":1267,"ch":129},"34640":{"sx":606,"sy":961,"sw":94,"sh":171},"701211":{"sx":606,"sy":703,"sw":240,"sh":135,"cy":110},"701224":{"sx":453,"sy":519,"sw":14,"sh":1,"cw":94},"701278":{"sx":702,"sy":961,"sw":92,"sh":108},"701281":{"sx":648,"sy":290,"sw":91,"sh":18}}}}